{
  "format_version": "1.21.10",
  "minecraft:item": {
    "description": {
      "identifier": "kurokumaft:railgun_energy_bottle",
      "menu_category": {
        "category": "equipment"
      }
    },
    "components": {
      "minecraft:tags": {
        "tags": [
          "kurokumaft:bullet"
        ]
      },
      "minecraft:max_stack_size": 16,
      "minecraft:icon": "railgun_energy_bottle",
      "minecraft:allow_off_hand": true,
      "minecraft:display_name": {
        "value": "item.kurokumaft:railgun_energy_bottle.name"
      },
      "minecraft:projectile": {
        "projectile_entity": "kurokumaft:railgun_energy"
      }
    }
  }
}
