{
	"format_version": "1.16.0",
	"minecraft:geometry": [
		{
			"description": {
				"identifier": "geometry.kyokokukamusari",
				"texture_width": 128,
				"texture_height": 128,
				"visible_bounds_width": 19,
				"visible_bounds_height": 17,
				"visible_bounds_offset": [0, 3.5, 0]
			},
			"bones": [
				{
					"name": "nichirintou_hold_right",
					"pivot": [-6, 0, 0]
				},
				{
					"name": "nichirintou",
					"parent": "nichirintou_hold_right",
					"pivot": [-6, -2, 0],
					"binding": "q.item_slot_to_bone_name(c.item_slot)"
				},
				{
					"name": "blade",
					"parent": "nichirintou",
					"pivot": [-5, 0.50092, -71.13811]
				},
				{
					"name": "body3",
					"parent": "blade",
					"pivot": [-5, 0.50092, -71.13811]
				},
				{
					"name": "peak",
					"parent": "body3",
					"pivot": [-5, 0.50092, -71.13811],
					"cubes": [
						{
							"origin": [-6, 0.40092, -100.73811],
							"size": [1, 2, 83.4],
							"uv": {
								"north": {"uv": [65.125, 7.5], "uv_size": [8, 2]},
								"east": {"uv": [0.0625, 11], "uv_size": [79.6875, 2.1875]},
								"south": {"uv": [67, 10], "uv_size": [12, 3]},
								"west": {"uv": [0, 11], "uv_size": [81.5625, 1.9375]},
								"up": {"uv": [1, 7.8125], "uv_size": [81, 1.6875]},
								"down": {"uv": [1, 12.375], "uv_size": [81, -3.375]}
							}
						}
					]
				},
				{
					"name": "body2",
					"parent": "body3",
					"pivot": [-5, 0.50092, -71.13811]
				},
				{
					"name": "blade2",
					"parent": "body2",
					"pivot": [-5, 0.50092, -71.13811],
					"rotation": [0, 0, -12.5],
					"cubes": [
						{
							"origin": [-6, -1.27531, -99.13811],
							"size": [0, 1.9, 81.8],
							"uv": {
								"north": {"uv": [0, 0], "uv_size": [0, 1.9375]},
								"east": {"uv": [0, 16], "uv_size": [79.8125, 5.9375]},
								"south": {"uv": [0, 0], "uv_size": [0, 1.9375]},
								"west": {"uv": [0, 20], "uv_size": [81.8125, 1.9375]},
								"up": {"uv": [80, 22], "uv_size": [-80, -1.1875]},
								"down": {"uv": [81, 21.8125], "uv_size": [-68, -0.8125]}
							}
						}
					]
				},
				{
					"name": "blade3",
					"parent": "body2",
					"pivot": [-5, -1.39908, -95.33811],
					"rotation": [0, 0, 16.5],
					"cubes": [
						{
							"origin": [-5.51123, -1.6, -99.13811],
							"size": [0, 1.9, 81.8],
							"uv": {
								"north": {"uv": [0, 0], "uv_size": [0, 2]},
								"east": {"uv": [0, 20], "uv_size": [81.8125, 2]},
								"south": {"uv": [0, 0], "uv_size": [0, 2]},
								"west": {"uv": [0, 16], "uv_size": [81.8125, 6]},
								"up": {"uv": [82, 21], "uv_size": [-82, 0.8125]},
								"down": {"uv": [81, 21.8125], "uv_size": [-81, -0.8125]}
							}
						}
					]
				},
				{
					"name": "top",
					"parent": "blade",
					"pivot": [-5, 0.50092, -87.13811]
				},
				{
					"name": "left",
					"parent": "top",
					"pivot": [-2.1, 0.00092, -99.63811],
					"rotation": [-0.08748, -4.99924, 1.2]
				},
				{
					"name": "blade4",
					"parent": "left",
					"pivot": [-4.80481, -0.39579, -100.85349],
					"rotation": [-3.3024, 4.95122, 14.53016],
					"cubes": [
						{
							"origin": [-5.32284, -1.57593, -99.81823],
							"size": [0, 2, 1],
							"uv": {
								"north": {"uv": [37, 16], "uv_size": [14, 4]},
								"east": {"uv": [51, 17], "uv_size": [11, 3]},
								"south": {"uv": [36, 16], "uv_size": [14, 4]},
								"west": {"uv": [64, 17.1], "uv_size": [10.8, 3.9]},
								"up": {"uv": [50, 16], "uv_size": [-13, 4]},
								"down": {"uv": [50, 20], "uv_size": [-12, -4]}
							}
						}
					]
				},
				{
					"name": "blade5",
					"parent": "left",
					"pivot": [-5.65481, -1.29579, -101.50349],
					"rotation": [-4.05259, 7.53866, 13.91607],
					"cubes": [
						{
							"origin": [-5.7231, -1.36301, -100.81815],
							"size": [0, 2, 1],
							"uv": {
								"north": {"uv": [42, 16], "uv_size": [9, 4]},
								"east": {"uv": [49, 16], "uv_size": [10, 3]},
								"south": {"uv": [45, 16], "uv_size": [11, 4]},
								"west": {"uv": [66, 17], "uv_size": [-7, 4]},
								"up": {"uv": [56, 17], "uv_size": [-13, 4]},
								"down": {"uv": [56, 20], "uv_size": [-9, -4]}
							}
						}
					]
				},
				{
					"name": "blade6",
					"parent": "left",
					"pivot": [-5.65481, -1.59579, -101.00349],
					"rotation": [-6.82411, 7.79074, 13.46097],
					"cubes": [
						{
							"origin": [-5.7247, -1.41358, -101.85476],
							"size": [0, 2, 1],
							"uv": {
								"north": {"uv": [40, 16], "uv_size": [13, 4]},
								"east": {"uv": [47, 17], "uv_size": [9, 3]},
								"south": {"uv": [43, 16], "uv_size": [14, 4]},
								"west": {"uv": [59, 16], "uv_size": [8, 6]},
								"up": {"uv": [55, 16], "uv_size": [-11, 4]},
								"down": {"uv": [53, 20], "uv_size": [-10, -4]}
							}
						}
					]
				},
				{
					"name": "blade7",
					"parent": "left",
					"pivot": [-5.75481, -1.19579, -102.10349],
					"rotation": [-18.87787, 10.68414, 12.67494],
					"cubes": [
						{
							"origin": [-5.80104, -1.18125, -102.80203],
							"size": [0, 1.9, 1],
							"uv": {
								"north": {"uv": [35, 16], "uv_size": [8, 3.875]},
								"east": {"uv": [35, 16], "uv_size": [12, 3.875]},
								"south": {"uv": [35, 15], "uv_size": [9, 3.875]},
								"west": {"uv": [61, 17], "uv_size": [-5, 3.875]},
								"up": {"uv": [44, 16], "uv_size": [-10, 3]},
								"down": {"uv": [46, 20], "uv_size": [-9, -4]}
							}
						}
					]
				},
				{
					"name": "blade8",
					"parent": "left",
					"pivot": [-5.85481, -0.79579, -103.00349],
					"rotation": [-21.67613, 11.51727, 11.62999],
					"cubes": [
						{
							"origin": [-5.89189, -0.81893, -103.71284],
							"size": [0, 1.7, 1],
							"uv": {
								"north": {"uv": [19, 16], "uv_size": [8, 3.6875]},
								"east": {"uv": [25, 16], "uv_size": [14, 3.6875]},
								"south": {"uv": [5, 16], "uv_size": [11, 3.6875]},
								"west": {"uv": [28.6, 16.8], "uv_size": [11.2, 4.1875]},
								"up": {"uv": [17, 15], "uv_size": [-11, 4]},
								"down": {"uv": [18, 20], "uv_size": [-10, -4]}
							}
						}
					]
				},
				{
					"name": "blade9",
					"parent": "left",
					"pivot": [-5.55481, -0.49579, -103.90349],
					"rotation": [-32.05894, 13.63032, 9.88934],
					"cubes": [
						{
							"origin": [-6.0093, -0.50208, -104.72228],
							"size": [0, 1.3, 1],
							"uv": {
								"north": {"uv": [9, 16], "uv_size": [12, 3.3125]},
								"east": {"uv": [54, 16], "uv_size": [12, 4.3125]},
								"south": {"uv": [21, 16], "uv_size": [10, 4.3125]},
								"west": {"uv": [31, 17.6], "uv_size": [13, 3.7125]},
								"up": {"uv": [37, 16], "uv_size": [-12, 4]},
								"down": {"uv": [37, 21], "uv_size": [-11, -5]}
							}
						}
					]
				},
				{
					"name": "blade10",
					"parent": "left",
					"pivot": [-6.05481, 0.20421, -104.80349],
					"rotation": [-37.37748, 12.53778, 7.98779],
					"cubes": [
						{
							"origin": [-6.12024, 0.26564, -105.44176],
							"size": [0, 1.2, 1],
							"uv": {
								"north": {"uv": [34, 16], "uv_size": [13, 3.1875]},
								"east": {"uv": [43, 16], "uv_size": [12, 4.1875]},
								"south": {"uv": [36, 16], "uv_size": [13, 4.1875]},
								"west": {"uv": [27, 18], "uv_size": [11, 3.1875]},
								"up": {"uv": [45, 15], "uv_size": [-10, 5]},
								"down": {"uv": [46, 20], "uv_size": [-10, -3]}
							}
						}
					]
				},
				{
					"name": "blade11",
					"parent": "left",
					"pivot": [-6.15481, 0.70421, -103.50349],
					"rotation": [-65.2931, 13.21654, 4.12416],
					"cubes": [
						{
							"origin": [-5.75867, -0.86527, -104.98775],
							"size": [0, 1.1, 1],
							"uv": {
								"north": {"uv": [3, 15], "uv_size": [13, 3.125]},
								"east": {"uv": [17, 16], "uv_size": [11, 3.125]},
								"south": {"uv": [6, 16], "uv_size": [9, 4.125]},
								"west": {"uv": [18, 18.4], "uv_size": [11, 3.025]},
								"up": {"uv": [16, 15], "uv_size": [-11, 3]},
								"down": {"uv": [18, 19], "uv_size": [-14, -3]}
							}
						}
					]
				},
				{
					"name": "blade12",
					"parent": "left",
					"pivot": [-6.05481, 1.50421, -105.20349],
					"rotation": [-76.42207, 16.57181, 3.02557],
					"cubes": [
						{
							"origin": [-6.08, 1.09092, -105.57048],
							"size": [0, 1, 1],
							"uv": {
								"north": {"uv": [4, 16], "uv_size": [9, 4]},
								"east": {"uv": [32, 15], "uv_size": [12, 5]},
								"south": {"uv": [22, 15], "uv_size": [10, 5]},
								"west": {"uv": [32, 18.6], "uv_size": [7, 2.4]},
								"up": {"uv": [22, 16], "uv_size": [-13, 4]},
								"down": {"uv": [15, 20], "uv_size": [-12, -4]}
							}
						}
					]
				},
				{
					"name": "blade26",
					"parent": "left",
					"pivot": [-6.05481, 1.60421, -105.30349],
					"rotation": [-91.46404, 15.65073, -1.33709],
					"cubes": [
						{
							"origin": [-6.10031, 1.22332, -106.01811],
							"size": [0, 1.1, 0.8],
							"uv": {
								"north": {"uv": [24, 16], "uv_size": [6, 4.125]},
								"east": {"uv": [41, 17], "uv_size": [8.8125, 4.125]},
								"south": {"uv": [12, 17], "uv_size": [13, 3.125]},
								"west": {"uv": [29, 18.1], "uv_size": [9.8125, 3.325]},
								"up": {"uv": [29, 16], "uv_size": [-8, 3.8125]},
								"down": {"uv": [20, 20.8125], "uv_size": [-10, -4.8125]}
							}
						}
					]
				},
				{
					"name": "right",
					"parent": "top",
					"pivot": [-8.1, -0.49908, -99.63811],
					"rotation": [1.38143, -4.80584, -15.86179]
				},
				{
					"name": "blade13",
					"parent": "right",
					"pivot": [-6.00481, -0.39579, -99.85349],
					"rotation": [-4.26882, 3.36647, 2.54607],
					"cubes": [
						{
							"origin": [-5.8473, -2.11058, -100.22056],
							"size": [0, 2, 1],
							"uv": {
								"north": {"uv": [51, 16], "uv_size": [11, 3]},
								"east": {"uv": [55, 17], "uv_size": [10, 4]},
								"south": {"uv": [49, 16], "uv_size": [9, 3]},
								"west": {"uv": [55, 16], "uv_size": [8, 3]},
								"up": {"uv": [0, 0], "uv_size": [0, 1]},
								"down": {"uv": [62, 19], "uv_size": [-12, -3]}
							}
						}
					]
				},
				{
					"name": "blade14",
					"parent": "right",
					"pivot": [-6.15481, -0.59579, -100.70349],
					"rotation": [-7.50842, 4.54941, 2.13013],
					"cubes": [
						{
							"origin": [-5.92931, -2.01485, -101.14612],
							"size": [0, 1.9, 1],
							"uv": {
								"north": {"uv": [49, 17], "uv_size": [12, 2.875]},
								"east": {"uv": [60, 17], "uv_size": [8, 3.875]},
								"south": {"uv": [51, 17], "uv_size": [13, 2.875]},
								"west": {"uv": [64, 16], "uv_size": [9, 1.875]},
								"up": {"uv": [63, 17], "uv_size": [-12, 2]},
								"down": {"uv": [62, 19], "uv_size": [-10, -2]}
							}
						}
					]
				},
				{
					"name": "blade15",
					"parent": "right",
					"pivot": [-5.95481, -0.59579, -101.50349],
					"rotation": [-10.50842, 4.54941, 2.13013],
					"cubes": [
						{
							"origin": [-5.99199, -1.92008, -102.07023],
							"size": [0, 1.9, 1],
							"uv": {
								"north": {"uv": [53, 17], "uv_size": [10, 2.875]},
								"east": {"uv": [57, 17], "uv_size": [7.8, 3.875]},
								"south": {"uv": [54, 17], "uv_size": [10, 2.875]},
								"west": {"uv": [57, 17], "uv_size": [9, 2.875]},
								"up": {"uv": [63, 17], "uv_size": [-8, 3]},
								"down": {"uv": [65, 20], "uv_size": [-8, -3]}
							}
						}
					]
				},
				{
					"name": "blade16",
					"parent": "right",
					"pivot": [-5.95481, -0.59579, -102.50349],
					"rotation": [-19.4536, 1.72108, 3.13201],
					"cubes": [
						{
							"origin": [-6.04043, -1.65954, -102.91112],
							"size": [0, 1.8, 1],
							"uv": {
								"north": {"uv": [30, 15], "uv_size": [5, 1.8125]},
								"east": {"uv": [36, 17], "uv_size": [5, 3.8125]},
								"south": {"uv": [29, 17], "uv_size": [7, 1.8125]},
								"west": {"uv": [32, 16], "uv_size": [7, 2.8125]},
								"up": {"uv": [38, 16], "uv_size": [-8, 2]},
								"down": {"uv": [37, 19], "uv_size": [-5, -2]}
							}
						}
					]
				},
				{
					"name": "blade17",
					"parent": "right",
					"pivot": [-6.15481, -0.99579, -104.10349],
					"rotation": [-33.46247, -1.27178, 3.73827],
					"cubes": [
						{
							"origin": [-6.07578, -1.04045, -105.16797],
							"size": [0, 1.4, 1.1],
							"uv": {
								"north": {"uv": [19, 16], "uv_size": [9, 3.375]},
								"east": {"uv": [15, 16], "uv_size": [14.125, 5.375]},
								"south": {"uv": [19, 16], "uv_size": [10, 3.375]},
								"west": {"uv": [20, 17], "uv_size": [10.125, 2.375]},
								"up": {"uv": [28, 16], "uv_size": [-9, 3.125]},
								"down": {"uv": [29, 16.125], "uv_size": [-8, 2.875]}
							}
						}
					]
				},
				{
					"name": "blade18",
					"parent": "right",
					"pivot": [-6.15481, -1.39579, -103.30349],
					"rotation": [-24.45405, 0.39685, 2.63562],
					"cubes": [
						{
							"origin": [-6.08863, -1.40793, -104.26171],
							"size": [0, 1.6, 1.1],
							"uv": {
								"north": {"uv": [5, 16], "uv_size": [9, 1.625]},
								"east": {"uv": [12, 17.2], "uv_size": [6.025, 3.425]},
								"south": {"uv": [4, 16], "uv_size": [7, 2.625]},
								"west": {"uv": [7, 16], "uv_size": [8.125, 2.625]},
								"up": {"uv": [11, 16], "uv_size": [-7, 2.125]},
								"down": {"uv": [12, 18.125], "uv_size": [-8, -2.125]}
							}
						}
					]
				},
				{
					"name": "blade19",
					"parent": "right",
					"pivot": [-5.95481, 1.10421, -105.10349],
					"rotation": [-39.3552, -4.72115, 2.68873],
					"cubes": [
						{
							"origin": [-5.90378, -0.00467, -105.04833],
							"size": [0, 1.1, 1.1],
							"uv": {
								"north": {"uv": [7, 16], "uv_size": [11, 3.125]},
								"east": {"uv": [6, 16], "uv_size": [12.125, 5.125]},
								"south": {"uv": [6, 17], "uv_size": [10, 3.125]},
								"west": {"uv": [10, 16], "uv_size": [10.125, 2.125]},
								"up": {"uv": [18, 16], "uv_size": [-11, 3.125]},
								"down": {"uv": [19, 19.125], "uv_size": [-13, -3.125]}
							}
						}
					]
				},
				{
					"name": "blade20",
					"parent": "right",
					"pivot": [-5.95481, 0.70421, -104.80349],
					"rotation": [-66.59739, -10.04566, 8.44216],
					"cubes": [
						{
							"origin": [-5.99209, -0.409, -105.70198],
							"size": [0, 1, 1],
							"uv": {
								"north": {"uv": [3, 16], "uv_size": [10, 3]},
								"east": {"uv": [5, 17.8], "uv_size": [12, 3.2]},
								"south": {"uv": [6, 16], "uv_size": [10, 4]},
								"west": {"uv": [10, 16], "uv_size": [9, 2]},
								"up": {"uv": [17, 16], "uv_size": [-11, 3]},
								"down": {"uv": [16, 20], "uv_size": [-10, -4]}
							}
						}
					]
				},
				{
					"name": "blade21",
					"parent": "right",
					"pivot": [-5.95481, 0.00421, -105.10349],
					"rotation": [-78.56771, -10.98354, 12.11256],
					"cubes": [
						{
							"origin": [-6.11486, -0.78665, -106.97791],
							"size": [0, 1, 0.8],
							"uv": {
								"north": {"uv": [8, 16], "uv_size": [9, 4]},
								"east": {"uv": [12, 18.2], "uv_size": [11.7125, 2.8]},
								"south": {"uv": [8, 17], "uv_size": [9, 3]},
								"west": {"uv": [22, 16], "uv_size": [13.8125, 4]},
								"up": {"uv": [16, 16], "uv_size": [-10, 3.8125]},
								"down": {"uv": [15, 18.8125], "uv_size": [-7, -3.8125]}
							}
						}
					]
				},
				{
					"name": "blade22",
					"parent": "right",
					"pivot": [-5.75481, 1.10421, -105.80349],
					"rotation": [-91.70789, -8.42554, 16.83428],
					"cubes": [
						{
							"origin": [-5.77, 0.72332, -106.51811],
							"size": [0, 1, 0.9],
							"uv": {
								"north": {"uv": [0, 0], "uv_size": [0, 1]},
								"east": {"uv": [66, 19.1], "uv_size": [8.775, 1.9]},
								"south": {"uv": [0, 0], "uv_size": [0, 1]},
								"west": {"uv": [67, 16], "uv_size": [5.875, 3]},
								"up": {"uv": [0, 0], "uv_size": [0, 0.875]},
								"down": {"uv": [0, 0.875], "uv_size": [0, -0.875]}
							}
						}
					]
				},
				{
					"name": "peak2",
					"parent": "top",
					"pivot": [-5, 0.50092, -87.13811]
				},
				{
					"name": "peak3",
					"parent": "peak2",
					"pivot": [-5, 0.50092, -99.13811],
					"rotation": [0, 1, 0],
					"cubes": [
						{
							"origin": [-5, 0.40092, -100.93811],
							"size": [0, 2, 1.7],
							"uv": {
								"north": {"uv": [0, 0], "uv_size": [0, 2]},
								"east": {"uv": [46, 8], "uv_size": [1.6875, 2]},
								"south": {"uv": [0, 0], "uv_size": [0, 2]},
								"west": {"uv": [48, 8], "uv_size": [1.6875, 2]},
								"up": {"uv": [0, 0], "uv_size": [0, 1.6875]},
								"down": {"uv": [0, 1.6875], "uv_size": [0, -1.6875]}
							}
						}
					]
				},
				{
					"name": "peak4",
					"parent": "peak2",
					"pivot": [-5, 1.00092, -100.93811],
					"rotation": [0, 4, 0],
					"cubes": [
						{
							"origin": [-5.64418, 0.49776, -102.1407],
							"size": [0.6, 1.9, 1.5],
							"uv": {
								"north": {"uv": [67.125, 7.1875], "uv_size": [4.75, 2.375]},
								"east": {"uv": [54.4375, 7.25], "uv_size": [3.8125, 1.375]},
								"south": {"uv": [55.25, 7.375], "uv_size": [3.125, 1.375]},
								"west": {"uv": [67.8125, 11.1875], "uv_size": [3.25, 2.75]},
								"up": {"uv": [65.25, 7.75], "uv_size": [3.625, 1.25]},
								"down": {"uv": [70, 12.5], "uv_size": [9.625, -3.5]}
							}
						}
					]
				},
				{
					"name": "peak5",
					"parent": "peak2",
					"pivot": [-5.2, 2.40092, -102.13811],
					"rotation": [0.07011, 5.99909, 1.00459],
					"cubes": [
						{
							"origin": [-5.62856, 0.60653, -103.22842],
							"size": [0.5, 1.8, 1.2],
							"uv": {
								"north": {"uv": [66.25, 7.875], "uv_size": [3.4375, 1.875]},
								"east": {"uv": [56, 7.375], "uv_size": [4.75, 1]},
								"south": {"uv": [58.1875, 7.3125], "uv_size": [3, 1.625]},
								"west": {"uv": [67.625, 11.375], "uv_size": [2.1875, 2.8125]},
								"up": {"uv": [68, 7.1875], "uv_size": [4.1875, 1.5625]},
								"down": {"uv": [67, 12.1875], "uv_size": [10.5, -3.1875]}
							}
						}
					]
				},
				{
					"name": "peak6",
					"parent": "peak2",
					"pivot": [-5.1, 2.40092, -103.23811],
					"rotation": [0.14025, 5.99755, 2.00979],
					"cubes": [
						{
							"origin": [-5.54312, 0.80225, -104.2449],
							"size": [0.3, 1.6, 1.1],
							"uv": {
								"north": {"uv": [62.0625, 7.25], "uv_size": [3.25, 1.375]},
								"east": {"uv": [71, 10], "uv_size": [7.125, 2.625]},
								"south": {"uv": [62, 9], "uv_size": [10.3125, 3.625]},
								"west": {"uv": [57.625, 10.8125], "uv_size": [2.625, 3.3125]},
								"up": {"uv": [68.25, 7.5625], "uv_size": [3.9375, 1.25]},
								"down": {"uv": [60, 13.125], "uv_size": [7.3125, -3.125]}
							}
						}
					]
				},
				{
					"name": "peak12",
					"parent": "peak2",
					"pivot": [-5.1, 2.40092, -104.23811],
					"rotation": [0.14025, 5.99755, 2.00979],
					"cubes": [
						{
							"origin": [-5.64312, 1.30225, -104.9449],
							"size": [0.3, 1.1, 0.8],
							"uv": {
								"north": {"uv": [65.125, 8.25], "uv_size": [5.25, 1.25]},
								"east": {"uv": [64.3125, 7.3125], "uv_size": [1.5625, 1.375]},
								"south": {"uv": [65.6875, 7.25], "uv_size": [3.875, 1.25]},
								"west": {"uv": [56.2875, 11.3375], "uv_size": [1.5, 2.8125]},
								"up": {"uv": [67.0625, 7.875], "uv_size": [4.25, 1.6875]},
								"down": {"uv": [67, 9.125], "uv_size": [4.125, -1.4375]}
							}
						}
					]
				},
				{
					"name": "peak7",
					"parent": "peak2",
					"pivot": [-5, 0.50092, -99.13811],
					"rotation": [0, 1, 0],
					"cubes": [
						{
							"origin": [-6, 0.40092, -100.83811],
							"size": [0, 2, 1.7],
							"uv": {
								"north": {"uv": [27, 9], "uv_size": [13, 4]},
								"east": {"uv": [36, 11.3125], "uv_size": [3.375, 2.1875]},
								"south": {"uv": [28, 9], "uv_size": [12, 4]},
								"west": {"uv": [39, 8], "uv_size": [7.6875, 4]},
								"up": {"uv": [39, 9], "uv_size": [-12, 3.6875]},
								"down": {"uv": [40, 12.6875], "uv_size": [-13, -3.6875]}
							}
						}
					]
				},
				{
					"name": "peak8",
					"parent": "peak2",
					"pivot": [-6, 1.00092, -100.93811],
					"rotation": [0.01745, -0.99985, -1.00015],
					"cubes": [
						{
							"origin": [-6, 0.49776, -102.2407],
							"size": [0.5, 1.9, 1.5],
							"uv": {
								"north": {"uv": [46, 7.25], "uv_size": [5.3125, 1]},
								"east": {"uv": [46.25, 11.1875], "uv_size": [2, 2.625]},
								"south": {"uv": [45.3125, 7.875], "uv_size": [2.8125, 1.5625]},
								"west": {"uv": [42.875, 7.375], "uv_size": [3.75, 1.4375]},
								"up": {"uv": [46.5, 7.25], "uv_size": [3.4375, 2.125]},
								"down": {"uv": [43.75, 8.6875], "uv_size": [4.625, -1.375]}
							}
						}
					]
				},
				{
					"name": "peak9",
					"parent": "peak2",
					"pivot": [-6, 2.20092, -101.93811],
					"rotation": [0.06983, -3.00091, 0.99361],
					"cubes": [
						{
							"origin": [-6.01565, 0.72066, -103.14383],
							"size": [0.4, 1.7, 1.2],
							"uv": {
								"north": {"uv": [42.625, 7.1875], "uv_size": [2.375, 2.375]},
								"east": {"uv": [45.375, 10.5625], "uv_size": [3.0625, 2.8125]},
								"south": {"uv": [41.375, 7.625], "uv_size": [1.6875, 1.125]},
								"west": {"uv": [39.125, 7.125], "uv_size": [4.25, 1.0625]},
								"up": {"uv": [53.1875, 7.4375], "uv_size": [5.0625, 2.125]},
								"down": {"uv": [54.4375, 8.8125], "uv_size": [1.6875, -1.5]}
							}
						}
					]
				},
				{
					"name": "peak10",
					"parent": "peak2",
					"pivot": [-5.8, 2.40092, -103.23811],
					"rotation": [0.24428, -1.99573, -0.01064],
					"cubes": [
						{
							"origin": [-5.94312, 0.75225, -104.0449],
							"size": [0.6, 1.65, 1],
							"uv": {
								"north": {"uv": [66.8125, 7.9375], "uv_size": [6.1875, 1.875]},
								"east": {"uv": [45.65, 11.2625], "uv_size": [1.975, 2.95]},
								"south": {"uv": [43.4375, 7.375], "uv_size": [4.6875, 1.1875]},
								"west": {"uv": [46.8, 7.275], "uv_size": [2.875, 1.2875]},
								"up": {"uv": [67.4375, 7.4375], "uv_size": [4.3125, 1.5625]},
								"down": {"uv": [43.875, 8.9375], "uv_size": [3.75, -0.9375]}
							}
						}
					]
				},
				{
					"name": "peak11",
					"parent": "peak2",
					"pivot": [-5.8, 1.00092, -104.23811],
					"rotation": [0.47007, -1.99324, 0.00414],
					"cubes": [
						{
							"origin": [-5.91799, 1.05198, -104.93386],
							"size": [0.3, 1.35, 0.9],
							"uv": {
								"north": {"uv": [71.3125, 7.375], "uv_size": [3.5625, 1.75]},
								"east": {"uv": [46.0625, 11.15], "uv_size": [2, 3.3125]},
								"south": {"uv": [49.75, 7.5], "uv_size": [3.6875, 0.3125]},
								"west": {"uv": [47.5, 7.125], "uv_size": [3.8125, 1.375]},
								"up": {"uv": [69, 7.1875], "uv_size": [3.5625, 2.0625]},
								"down": {"uv": [49.0625, 8.9375], "uv_size": [4.9375, -1.375]}
							}
						}
					]
				},
				{
					"name": "handle",
					"parent": "nichirintou",
					"pivot": [-5, 0.50092, -15.33811],
					"cubes": [
						{
							"origin": [-6.3, -1.69908, -19.83811],
							"size": [1.6, 4.4, 2.65],
							"uv": {
								"north": {"uv": [77.625, 81.3125], "uv_size": [4.5625, 4.875]},
								"east": {"uv": [79.25, 82.125], "uv_size": [5.4375, 4.6875]},
								"south": {"uv": [77.5625, 83.8125], "uv_size": [4.4375, 3.8125]},
								"west": {"uv": [77.9375, 81.9375], "uv_size": [5.8125, 4.1875]},
								"up": {"uv": [77.8125, 81.625], "uv_size": [5.1875, 4.875]},
								"down": {"uv": [77.875, 86], "uv_size": [6.25, -4.5625]}
							}
						}
					]
				},
				{
					"name": "grip",
					"parent": "handle",
					"pivot": [-5, 0.50092, -15.33811],
					"cubes": [
						{
							"origin": [-6.2, -1.69908, -17.43811],
							"size": [1.4, 4.3, 41.7],
							"uv": {
								"north": {"uv": [20, 26], "uv_size": [9.375, 1.3125]},
								"east": {"uv": [0, 0], "uv_size": [41.6875, 4.3125]},
								"south": {"uv": [31, 25], "uv_size": [12.375, 2.3125]},
								"west": {"uv": [0, 0], "uv_size": [41.6875, 4.3125]},
								"up": {"uv": [1, 25], "uv_size": [82.375, 2.6875]},
								"down": {"uv": [0, 27.6875], "uv_size": [80.375, -2.6875]}
							}
						},
						{
							"origin": [-6.2, -1.69908, 24.26189],
							"size": [1.4, 4.3, 1.7],
							"uv": {
								"north": {"uv": [69.3125, 68.875], "uv_size": [3.375, 5.8125]},
								"east": {"uv": [69.8125, 67.3125], "uv_size": [3.375, 3.9375]},
								"south": {"uv": [68.5, 67.6875], "uv_size": [4.5625, 4.3125]},
								"west": {"uv": [70.6875, 68.5], "uv_size": [2.5625, 3]},
								"up": {"uv": [69.5625, 68.25], "uv_size": [3.1875, 3.6875]},
								"down": {"uv": [75.3125, 67.625], "uv_size": [-6.625, 7]}
							}
						}
					]
				},
				{
					"name": "flange",
					"parent": "handle",
					"pivot": [-5.3, 0.50092, -18.93811],
					"cubes": [
						{
							"origin": [-6.95, -2.84908, -18.93811],
							"size": [3, 7, 1],
							"uv": {
								"north": {"uv": [77.625, 67.6875], "uv_size": [4.125, 3.4375]},
								"east": {"uv": [69.5625, 67.375], "uv_size": [4, 6.5625]},
								"south": {"uv": [77.625, 67.6875], "uv_size": [4.125, 3.4375]},
								"west": {"uv": [69.375, 68.0625], "uv_size": [4.875, 7]},
								"up": {"uv": [69.4375, 67.4375], "uv_size": [5.75, 4]},
								"down": {"uv": [68.875, 75.25], "uv_size": [5.75, -7]}
							}
						},
						{
							"origin": [-8.05, -1.79908, -18.93811],
							"size": [5, 5, 1],
							"uv": {
								"north": {"uv": [77.6875, 71.9375], "uv_size": [3.9375, 4.875]},
								"east": {"uv": [68.75, 67.125], "uv_size": [4.625, 8.5]},
								"south": {"uv": [77.6875, 71.5], "uv_size": [4.0625, 5.4375]},
								"west": {"uv": [69.5, 69.3125], "uv_size": [3.375, 5.375]},
								"up": {"uv": [69.5625, 67], "uv_size": [3.25, 6.3125]},
								"down": {"uv": [69.125, 67.1875], "uv_size": [4.375, 6.0625]}
							}
						}
					]
				},
				{
					"name": "top_blade1",
					"parent": "nichirintou",
					"pivot": [-5, -0.99908, -80.13811],
					"rotation": [-80, 0, 0]
				},
				{
					"name": "body4",
					"parent": "top_blade1",
					"pivot": [-5, -0.99908, -80.13811]
				},
				{
					"name": "peak13",
					"parent": "body4",
					"pivot": [-5, -0.99908, -80.13811],
					"cubes": [
						{
							"origin": [-6, -1.09908, -109.73811],
							"size": [1, 2, 26.4],
							"uv": {
								"north": {"uv": [14.375, 86.8125], "uv_size": [8, 1.6875]},
								"east": {"uv": [0.5625, 86.5], "uv_size": [48.625, 2.375]},
								"south": {"uv": [67, 10], "uv_size": [12, 3]},
								"west": {"uv": [0.875, 86.75], "uv_size": [34, 2.1875]},
								"up": {"uv": [13, 87.0625], "uv_size": [34.1875, 1.5625]},
								"down": {"uv": [15.8125, 88.5], "uv_size": [31.3125, -1.6875]}
							}
						}
					]
				},
				{
					"name": "body5",
					"parent": "body4",
					"pivot": [-5, -0.99908, -80.13811]
				},
				{
					"name": "blade24",
					"parent": "body5",
					"pivot": [-5, -0.99908, -80.13811],
					"rotation": [0, 0, -12.5],
					"cubes": [
						{
							"origin": [-6, -2.77531, -108.13811],
							"size": [0, 1.9, 24.8],
							"uv": {
								"north": {"uv": [0, 0], "uv_size": [0, 1.9375]},
								"east": {"uv": [0.1875, 79.875], "uv_size": [48.125, 1.8125]},
								"south": {"uv": [0, 0], "uv_size": [0, 1.9375]},
								"west": {"uv": [0, 20], "uv_size": [81.8125, 1.9375]},
								"up": {"uv": [80, 22], "uv_size": [-80, -1.1875]},
								"down": {"uv": [81, 21.8125], "uv_size": [-68, -0.8125]}
							}
						}
					]
				},
				{
					"name": "blade25",
					"parent": "body5",
					"pivot": [-5, -2.89908, -104.33811],
					"rotation": [0, 0, 16.5],
					"cubes": [
						{
							"origin": [-5.51123, -3.1, -108.13811],
							"size": [0, 1.9, 24.8],
							"uv": {
								"north": {"uv": [0, 0], "uv_size": [0, 2]},
								"east": {"uv": [0, 20], "uv_size": [81.8125, 2]},
								"south": {"uv": [0, 0], "uv_size": [0, 2]},
								"west": {"uv": [0.3125, 79.8125], "uv_size": [46.0625, 2.125]},
								"up": {"uv": [82, 21], "uv_size": [-82, 0.8125]},
								"down": {"uv": [81, 21.8125], "uv_size": [-81, -0.8125]}
							}
						}
					]
				},
				{
					"name": "top2",
					"parent": "top_blade1",
					"pivot": [-5, -0.99908, -96.13811]
				},
				{
					"name": "left2",
					"parent": "top2",
					"pivot": [-2.1, -1.49908, -108.63811],
					"rotation": [-0.08748, -4.99924, 1.2]
				},
				{
					"name": "blade27",
					"parent": "left2",
					"pivot": [-4.80481, -1.89579, -109.85349],
					"rotation": [-3.3024, 4.95122, 14.53016],
					"cubes": [
						{
							"origin": [-5.32284, -3.07593, -108.81823],
							"size": [0, 2, 1],
							"uv": {
								"north": {"uv": [37, 16], "uv_size": [14, 4]},
								"east": {"uv": [51, 17], "uv_size": [11, 3]},
								"south": {"uv": [36, 16], "uv_size": [14, 4]},
								"west": {"uv": [32.1875, 78.225], "uv_size": [2.8625, 3.525]},
								"up": {"uv": [50, 16], "uv_size": [-13, 4]},
								"down": {"uv": [50, 20], "uv_size": [-12, -4]}
							}
						}
					]
				},
				{
					"name": "blade28",
					"parent": "left2",
					"pivot": [-5.65481, -2.79579, -110.50349],
					"rotation": [-4.05259, 7.53866, 13.91607],
					"cubes": [
						{
							"origin": [-5.7231, -2.86301, -109.81815],
							"size": [0, 2, 1],
							"uv": {
								"north": {"uv": [42, 16], "uv_size": [9, 4]},
								"east": {"uv": [49, 16], "uv_size": [10, 3]},
								"south": {"uv": [45, 16], "uv_size": [11, 4]},
								"west": {"uv": [23, 78.875], "uv_size": [-3.1875, 3]},
								"up": {"uv": [56, 17], "uv_size": [-13, 4]},
								"down": {"uv": [56, 20], "uv_size": [-9, -4]}
							}
						}
					]
				},
				{
					"name": "blade29",
					"parent": "left2",
					"pivot": [-5.65481, -3.09579, -110.00349],
					"rotation": [-6.82411, 7.79074, 13.46097],
					"cubes": [
						{
							"origin": [-5.7247, -2.91358, -110.85476],
							"size": [0, 2, 1],
							"uv": {
								"north": {"uv": [40, 16], "uv_size": [13, 4]},
								"east": {"uv": [47, 17], "uv_size": [9, 3]},
								"south": {"uv": [43, 16], "uv_size": [14, 4]},
								"west": {"uv": [8.375, 78.8125], "uv_size": [3.875, 2.875]},
								"up": {"uv": [55, 16], "uv_size": [-11, 4]},
								"down": {"uv": [53, 20], "uv_size": [-10, -4]}
							}
						}
					]
				},
				{
					"name": "blade30",
					"parent": "left2",
					"pivot": [-5.75481, -2.69579, -111.10349],
					"rotation": [-18.87787, 10.68414, 12.67494],
					"cubes": [
						{
							"origin": [-5.80104, -2.68125, -111.80203],
							"size": [0, 1.9, 1],
							"uv": {
								"north": {"uv": [35, 16], "uv_size": [8, 3.875]},
								"east": {"uv": [35, 16], "uv_size": [12, 3.875]},
								"south": {"uv": [35, 15], "uv_size": [9, 3.875]},
								"west": {"uv": [37.4375, 77.9375], "uv_size": [-5, 3.875]},
								"up": {"uv": [44, 16], "uv_size": [-10, 3]},
								"down": {"uv": [46, 20], "uv_size": [-9, -4]}
							}
						}
					]
				},
				{
					"name": "blade31",
					"parent": "left2",
					"pivot": [-5.85481, -2.29579, -112.00349],
					"rotation": [-21.67613, 11.51727, 11.62999],
					"cubes": [
						{
							"origin": [-5.89189, -2.31893, -112.71284],
							"size": [0, 1.7, 1],
							"uv": {
								"north": {"uv": [19, 16], "uv_size": [8, 3.6875]},
								"east": {"uv": [25, 16], "uv_size": [14, 3.6875]},
								"south": {"uv": [5, 16], "uv_size": [11, 3.6875]},
								"west": {"uv": [31.6625, 79.3625], "uv_size": [5.0125, 2.75]},
								"up": {"uv": [17, 15], "uv_size": [-11, 4]},
								"down": {"uv": [18, 20], "uv_size": [-10, -4]}
							}
						}
					]
				},
				{
					"name": "blade32",
					"parent": "left2",
					"pivot": [-5.55481, -1.99579, -112.90349],
					"rotation": [-32.05894, 13.63032, 9.88934],
					"cubes": [
						{
							"origin": [-6.0093, -2.00208, -113.72228],
							"size": [0, 1.3, 1],
							"uv": {
								"north": {"uv": [9, 16], "uv_size": [12, 3.3125]},
								"east": {"uv": [54, 16], "uv_size": [12, 4.3125]},
								"south": {"uv": [21, 16], "uv_size": [10, 4.3125]},
								"west": {"uv": [19.75, 78.1], "uv_size": [3.625, 3.525]},
								"up": {"uv": [37, 16], "uv_size": [-12, 4]},
								"down": {"uv": [37, 21], "uv_size": [-11, -5]}
							}
						}
					]
				},
				{
					"name": "blade33",
					"parent": "left2",
					"pivot": [-6.05481, -1.29579, -113.80349],
					"rotation": [-37.37748, 12.53778, 7.98779],
					"cubes": [
						{
							"origin": [-6.12024, -1.23436, -114.44176],
							"size": [0, 1.2, 1],
							"uv": {
								"north": {"uv": [34, 16], "uv_size": [13, 3.1875]},
								"east": {"uv": [43, 16], "uv_size": [12, 4.1875]},
								"south": {"uv": [36, 16], "uv_size": [13, 4.1875]},
								"west": {"uv": [19.1875, 79.1875], "uv_size": [4.1875, 2.6875]},
								"up": {"uv": [45, 15], "uv_size": [-10, 5]},
								"down": {"uv": [46, 20], "uv_size": [-10, -3]}
							}
						}
					]
				},
				{
					"name": "blade34",
					"parent": "left2",
					"pivot": [-6.15481, -0.79579, -112.50349],
					"rotation": [-65.2931, 13.21654, 4.12416],
					"cubes": [
						{
							"origin": [-5.75867, -2.36527, -113.98775],
							"size": [0, 1.1, 1],
							"uv": {
								"north": {"uv": [3, 15], "uv_size": [13, 3.125]},
								"east": {"uv": [17, 16], "uv_size": [11, 3.125]},
								"south": {"uv": [6, 16], "uv_size": [9, 4.125]},
								"west": {"uv": [44.5, 79.0875], "uv_size": [4.1875, 2.525]},
								"up": {"uv": [16, 15], "uv_size": [-11, 3]},
								"down": {"uv": [18, 19], "uv_size": [-14, -3]}
							}
						}
					]
				},
				{
					"name": "blade35",
					"parent": "left2",
					"pivot": [-6.05481, 0.00421, -114.20349],
					"rotation": [-76.42207, 16.57181, 3.02557],
					"cubes": [
						{
							"origin": [-6.08, -0.40908, -114.57048],
							"size": [0, 1, 1],
							"uv": {
								"north": {"uv": [4, 16], "uv_size": [9, 4]},
								"east": {"uv": [32, 15], "uv_size": [12, 5]},
								"south": {"uv": [22, 15], "uv_size": [10, 5]},
								"west": {"uv": [32.375, 78.975], "uv_size": [3.375, 2.7125]},
								"up": {"uv": [22, 16], "uv_size": [-13, 4]},
								"down": {"uv": [15, 20], "uv_size": [-12, -4]}
							}
						}
					]
				},
				{
					"name": "blade36",
					"parent": "left2",
					"pivot": [-6.05481, 0.10421, -114.30349],
					"rotation": [-91.46404, 15.65073, -1.33709],
					"cubes": [
						{
							"origin": [-6.10031, -0.27668, -115.01811],
							"size": [0, 1.1, 0.8],
							"uv": {
								"north": {"uv": [24, 16], "uv_size": [6, 4.125]},
								"east": {"uv": [41, 17], "uv_size": [8.8125, 4.125]},
								"south": {"uv": [12, 17], "uv_size": [13, 3.125]},
								"west": {"uv": [32, 79.1625], "uv_size": [3.25, 2.6375]},
								"up": {"uv": [29, 16], "uv_size": [-8, 3.8125]},
								"down": {"uv": [39.1875, 89.125], "uv_size": [-7.5, -2.125]}
							}
						}
					]
				},
				{
					"name": "right2",
					"parent": "top2",
					"pivot": [-8.1, -1.99908, -108.63811],
					"rotation": [1.38143, -4.80584, -15.86179]
				},
				{
					"name": "blade37",
					"parent": "right2",
					"pivot": [-6.00481, -1.89579, -108.85349],
					"rotation": [-4.26882, 3.36647, 2.54607],
					"cubes": [
						{
							"origin": [-5.8473, -3.61058, -109.22056],
							"size": [0, 2, 1],
							"uv": {
								"north": {"uv": [51, 16], "uv_size": [11, 3]},
								"east": {"uv": [19.4375, 79.0625], "uv_size": [3.625, 2.75]},
								"south": {"uv": [49, 16], "uv_size": [9, 3]},
								"west": {"uv": [55, 16], "uv_size": [8, 3]},
								"up": {"uv": [0, 0], "uv_size": [0, 1]},
								"down": {"uv": [62, 19], "uv_size": [-12, -3]}
							}
						}
					]
				},
				{
					"name": "blade38",
					"parent": "right2",
					"pivot": [-6.15481, -2.09579, -109.70349],
					"rotation": [-7.50842, 4.54941, 2.13013],
					"cubes": [
						{
							"origin": [-5.92931, -3.51485, -110.14612],
							"size": [0, 1.9, 1],
							"uv": {
								"north": {"uv": [49, 17], "uv_size": [12, 2.875]},
								"east": {"uv": [46.375, 78.625], "uv_size": [2.6875, 3.0625]},
								"south": {"uv": [51, 17], "uv_size": [13, 2.875]},
								"west": {"uv": [64, 16], "uv_size": [9, 1.875]},
								"up": {"uv": [63, 17], "uv_size": [-12, 2]},
								"down": {"uv": [62, 19], "uv_size": [-10, -2]}
							}
						}
					]
				},
				{
					"name": "blade39",
					"parent": "right2",
					"pivot": [-5.95481, -2.09579, -110.50349],
					"rotation": [-10.50842, 4.54941, 2.13013],
					"cubes": [
						{
							"origin": [-5.99199, -3.42008, -111.07023],
							"size": [0, 1.9, 1],
							"uv": {
								"north": {"uv": [53, 17], "uv_size": [10, 2.875]},
								"east": {"uv": [8.5625, 79.1875], "uv_size": [2.8625, 2.5625]},
								"south": {"uv": [54, 17], "uv_size": [10, 2.875]},
								"west": {"uv": [57, 17], "uv_size": [9, 2.875]},
								"up": {"uv": [63, 17], "uv_size": [-8, 3]},
								"down": {"uv": [65, 20], "uv_size": [-8, -3]}
							}
						}
					]
				},
				{
					"name": "blade40",
					"parent": "right2",
					"pivot": [-5.95481, -2.09579, -111.50349],
					"rotation": [-19.4536, 1.72108, 3.13201],
					"cubes": [
						{
							"origin": [-6.04043, -3.15954, -111.91112],
							"size": [0, 1.8, 1],
							"uv": {
								"north": {"uv": [30, 15], "uv_size": [5, 1.8125]},
								"east": {"uv": [19.9375, 81.25], "uv_size": [3.25, -3.0625]},
								"south": {"uv": [29, 17], "uv_size": [7, 1.8125]},
								"west": {"uv": [32, 16], "uv_size": [7, 2.8125]},
								"up": {"uv": [38, 16], "uv_size": [-8, 2]},
								"down": {"uv": [37, 19], "uv_size": [-5, -2]}
							}
						}
					]
				},
				{
					"name": "blade41",
					"parent": "right2",
					"pivot": [-6.15481, -2.49579, -113.10349],
					"rotation": [-33.46247, -1.27178, 3.73827],
					"cubes": [
						{
							"origin": [-6.07578, -2.54045, -114.16797],
							"size": [0, 1.4, 1.1],
							"uv": {
								"north": {"uv": [19, 16], "uv_size": [9, 3.375]},
								"east": {"uv": [32.5625, 81.75], "uv_size": [4.0625, -2.8125]},
								"south": {"uv": [19, 16], "uv_size": [10, 3.375]},
								"west": {"uv": [20, 17], "uv_size": [10.125, 2.375]},
								"up": {"uv": [28, 16], "uv_size": [-9, 3.125]},
								"down": {"uv": [29, 16.125], "uv_size": [-8, 2.875]}
							}
						}
					]
				},
				{
					"name": "blade42",
					"parent": "right2",
					"pivot": [-6.15481, -2.89579, -112.30349],
					"rotation": [-24.45405, 0.39685, 2.63562],
					"cubes": [
						{
							"origin": [-6.08863, -2.90793, -113.26171],
							"size": [0, 1.6, 1.1],
							"uv": {
								"north": {"uv": [5, 16], "uv_size": [9, 1.625]},
								"east": {"uv": [45.125, 82.075], "uv_size": [3.5875, -3.2625]},
								"south": {"uv": [4, 16], "uv_size": [7, 2.625]},
								"west": {"uv": [7, 16], "uv_size": [8.125, 2.625]},
								"up": {"uv": [11, 16], "uv_size": [-7, 2.125]},
								"down": {"uv": [12, 18.125], "uv_size": [-8, -2.125]}
							}
						}
					]
				},
				{
					"name": "blade43",
					"parent": "right2",
					"pivot": [-5.95481, -0.39579, -114.10349],
					"rotation": [-39.3552, -4.72115, 2.68873],
					"cubes": [
						{
							"origin": [-5.90378, -1.50467, -114.04833],
							"size": [0, 1.1, 1.1],
							"uv": {
								"north": {"uv": [7, 16], "uv_size": [11, 3.125]},
								"east": {"uv": [32.875, 81.9375], "uv_size": [3.5, -3.5625]},
								"south": {"uv": [6, 17], "uv_size": [10, 3.125]},
								"west": {"uv": [10, 16], "uv_size": [10.125, 2.125]},
								"up": {"uv": [18, 16], "uv_size": [-11, 3.125]},
								"down": {"uv": [19, 19.125], "uv_size": [-13, -3.125]}
							}
						}
					]
				},
				{
					"name": "blade44",
					"parent": "right2",
					"pivot": [-5.95481, -0.79579, -113.80349],
					"rotation": [-66.59739, -10.04566, 8.44216],
					"cubes": [
						{
							"origin": [-5.99209, -1.909, -114.70198],
							"size": [0, 1, 1],
							"uv": {
								"north": {"uv": [3, 16], "uv_size": [10, 3]},
								"east": {"uv": [45.25, 81.4875], "uv_size": [4, -2.675]},
								"south": {"uv": [6, 16], "uv_size": [10, 4]},
								"west": {"uv": [10, 16], "uv_size": [9, 2]},
								"up": {"uv": [17, 16], "uv_size": [-11, 3]},
								"down": {"uv": [16, 20], "uv_size": [-10, -4]}
							}
						}
					]
				},
				{
					"name": "blade45",
					"parent": "right2",
					"pivot": [-5.95481, -1.49579, -114.10349],
					"rotation": [-78.56771, -10.98354, 12.11256],
					"cubes": [
						{
							"origin": [-6.11486, -2.28665, -115.97791],
							"size": [0, 1, 0.8],
							"uv": {
								"north": {"uv": [8, 16], "uv_size": [9, 4]},
								"east": {"uv": [30.25, 86.8875], "uv_size": [6.65, 1.6125]},
								"south": {"uv": [8, 17], "uv_size": [9, 3]},
								"west": {"uv": [22, 16], "uv_size": [13.8125, 4]},
								"up": {"uv": [16, 16], "uv_size": [-10, 3.8125]},
								"down": {"uv": [15, 18.8125], "uv_size": [-7, -3.8125]}
							}
						}
					]
				},
				{
					"name": "blade46",
					"parent": "right2",
					"pivot": [-5.75481, -0.39579, -114.80349],
					"rotation": [-91.70789, -8.42554, 16.83428],
					"cubes": [
						{
							"origin": [-5.77, -0.77668, -115.51811],
							"size": [0, 1, 0.9],
							"uv": {
								"north": {"uv": [0, 0], "uv_size": [0, 1]},
								"east": {"uv": [32.5, 82.0375], "uv_size": [4.275, -2.975]},
								"south": {"uv": [0, 0], "uv_size": [0, 1]},
								"west": {"uv": [67, 16], "uv_size": [5.875, 3]},
								"up": {"uv": [0, 0], "uv_size": [0, 0.875]},
								"down": {"uv": [0, 0.875], "uv_size": [0, -0.875]}
							}
						}
					]
				},
				{
					"name": "peak14",
					"parent": "top2",
					"pivot": [-5, -0.99908, -96.13811]
				},
				{
					"name": "peak15",
					"parent": "peak14",
					"pivot": [-5, -0.99908, -108.13811],
					"rotation": [0, 1, 0],
					"cubes": [
						{
							"origin": [-5, -1.09908, -109.93811],
							"size": [0, 2, 1.7],
							"uv": {
								"north": {"uv": [0, 0], "uv_size": [0, 2]},
								"east": {"uv": [46, 8], "uv_size": [1.6875, 2]},
								"south": {"uv": [0, 0], "uv_size": [0, 2]},
								"west": {"uv": [14.9375, 86.9375], "uv_size": [1.6875, 2]},
								"up": {"uv": [0, 0], "uv_size": [0, 1.6875]},
								"down": {"uv": [0, 1.6875], "uv_size": [0, -1.6875]}
							}
						}
					]
				},
				{
					"name": "peak16",
					"parent": "peak14",
					"pivot": [-5, -0.49908, -109.93811],
					"rotation": [0, 4, 0],
					"cubes": [
						{
							"origin": [-5.64418, -1.00224, -111.1407],
							"size": [0.6, 1.9, 1.5],
							"uv": {
								"north": {"uv": [34.25, 86.375], "uv_size": [4.75, 2.375]},
								"east": {"uv": [54.4375, 7.25], "uv_size": [3.8125, 1.375]},
								"south": {"uv": [55.25, 7.375], "uv_size": [3.125, 1.375]},
								"west": {"uv": [19.875, 87], "uv_size": [2.375, 1.5]},
								"up": {"uv": [19.5625, 86.375], "uv_size": [3.625, 1.25]},
								"down": {"uv": [16.1875, 88.4375], "uv_size": [7.125, -1.375]}
							}
						}
					]
				},
				{
					"name": "peak17",
					"parent": "peak14",
					"pivot": [-5.2, 0.90092, -111.13811],
					"rotation": [0.07011, 5.99909, 1.00459],
					"cubes": [
						{
							"origin": [-5.62856, -0.89347, -112.22842],
							"size": [0.5, 1.8, 1.2],
							"uv": {
								"north": {"uv": [26.75, 86.5625], "uv_size": [3.4375, 1.875]},
								"east": {"uv": [56, 7.375], "uv_size": [4.75, 1]},
								"south": {"uv": [58.1875, 7.3125], "uv_size": [3, 1.625]},
								"west": {"uv": [24, 87.1875], "uv_size": [2.1875, 1.375]},
								"up": {"uv": [19.4375, 87], "uv_size": [4.1875, 1.5625]},
								"down": {"uv": [32.375, 88.4375], "uv_size": [6.875, -1.5625]}
							}
						}
					]
				},
				{
					"name": "peak18",
					"parent": "peak14",
					"pivot": [-5.1, 0.90092, -112.23811],
					"rotation": [0.14025, 5.99755, 2.00979],
					"cubes": [
						{
							"origin": [-5.54312, -0.69775, -113.2449],
							"size": [0.3, 1.6, 1.1],
							"uv": {
								"north": {"uv": [27.75, 86.875], "uv_size": [3.25, 1.375]},
								"east": {"uv": [71, 10], "uv_size": [7.125, 2.625]},
								"south": {"uv": [62, 9], "uv_size": [10.3125, 3.625]},
								"west": {"uv": [32.375, 86.6875], "uv_size": [2.625, 2]},
								"up": {"uv": [22.6875, 87.125], "uv_size": [3.9375, 1.25]},
								"down": {"uv": [60, 13.125], "uv_size": [7.3125, -3.125]}
							}
						}
					]
				},
				{
					"name": "peak19",
					"parent": "peak14",
					"pivot": [-5.1, 0.90092, -113.23811],
					"rotation": [0.14025, 5.99755, 2.00979],
					"cubes": [
						{
							"origin": [-5.64312, -0.19775, -113.9449],
							"size": [0.3, 1.1, 0.8],
							"uv": {
								"north": {"uv": [32.4375, 86.75], "uv_size": [5.25, 1.25]},
								"east": {"uv": [64.3125, 7.3125], "uv_size": [1.5625, 1.375]},
								"south": {"uv": [65.6875, 7.25], "uv_size": [3.875, 1.25]},
								"west": {"uv": [17.6625, 86.8375], "uv_size": [3.6875, 1.375]},
								"up": {"uv": [17.1875, 87.4375], "uv_size": [4.25, 1.1875]},
								"down": {"uv": [37.6875, 88.1875], "uv_size": [4.125, -1.3125]}
							}
						}
					]
				},
				{
					"name": "peak20",
					"parent": "peak14",
					"pivot": [-5, -0.99908, -108.13811],
					"rotation": [0, 1, 0],
					"cubes": [
						{
							"origin": [-6, -1.09908, -109.83811],
							"size": [0, 2, 1.7],
							"uv": {
								"north": {"uv": [27, 9], "uv_size": [13, 4]},
								"east": {"uv": [7.5625, 86.6875], "uv_size": [3.375, 2.1875]},
								"south": {"uv": [28, 9], "uv_size": [12, 4]},
								"west": {"uv": [39, 8], "uv_size": [7.6875, 4]},
								"up": {"uv": [39, 9], "uv_size": [-12, 3.6875]},
								"down": {"uv": [40, 12.6875], "uv_size": [-13, -3.6875]}
							}
						}
					]
				},
				{
					"name": "peak21",
					"parent": "peak14",
					"pivot": [-6, -0.49908, -109.93811],
					"rotation": [0.01745, -0.99985, -1.00015],
					"cubes": [
						{
							"origin": [-6, -1.00224, -111.2407],
							"size": [0.5, 1.9, 1.5],
							"uv": {
								"north": {"uv": [46, 7.25], "uv_size": [5.3125, 1]},
								"east": {"uv": [16.25, 87.125], "uv_size": [4.25, 1.5625]},
								"south": {"uv": [45.3125, 7.875], "uv_size": [2.8125, 1.5625]},
								"west": {"uv": [42.875, 7.375], "uv_size": [3.75, 1.4375]},
								"up": {"uv": [34.4375, 86.875], "uv_size": [3.4375, 2.125]},
								"down": {"uv": [43.75, 8.6875], "uv_size": [4.625, -1.375]}
							}
						}
					]
				},
				{
					"name": "peak22",
					"parent": "peak14",
					"pivot": [-6, 0.70092, -110.93811],
					"rotation": [0.06983, -3.00091, 0.99361],
					"cubes": [
						{
							"origin": [-6.01565, -0.77934, -112.14383],
							"size": [0.4, 1.7, 1.2],
							"uv": {
								"north": {"uv": [42.625, 7.1875], "uv_size": [2.375, 2.375]},
								"east": {"uv": [19.3125, 87.3125], "uv_size": [3.0625, 1.5]},
								"south": {"uv": [41.375, 7.625], "uv_size": [1.6875, 1.125]},
								"west": {"uv": [39.125, 7.125], "uv_size": [4.25, 1.0625]},
								"up": {"uv": [33.875, 86.5625], "uv_size": [5.0625, 2.125]},
								"down": {"uv": [54.4375, 8.8125], "uv_size": [1.6875, -1.5]}
							}
						}
					]
				},
				{
					"name": "peak23",
					"parent": "peak14",
					"pivot": [-5.8, 0.90092, -112.23811],
					"rotation": [0.24428, -1.99573, -0.01064],
					"cubes": [
						{
							"origin": [-5.94312, -0.74775, -113.0449],
							"size": [0.6, 1.65, 1],
							"uv": {
								"north": {"uv": [16.5, 86.625], "uv_size": [6.1875, 1.875]},
								"east": {"uv": [20.4625, 86.7], "uv_size": [2.975, 1.95]},
								"south": {"uv": [43.4375, 7.375], "uv_size": [4.6875, 1.1875]},
								"west": {"uv": [37.8, 87.2125], "uv_size": [2.875, 1.2875]},
								"up": {"uv": [21.75, 86.75], "uv_size": [4.3125, 1.5625]},
								"down": {"uv": [26.25, 88.625], "uv_size": [3.9375, -1.8125]}
							}
						}
					]
				},
				{
					"name": "peak24",
					"parent": "peak14",
					"pivot": [-5.8, -0.49908, -113.23811],
					"rotation": [0.47007, -1.99324, 0.00414],
					"cubes": [
						{
							"origin": [-5.91799, -0.44802, -113.93386],
							"size": [0.3, 1.35, 0.9],
							"uv": {
								"north": {"uv": [71.3125, 7.375], "uv_size": [3.5625, 1.75]},
								"east": {"uv": [18.875, 87.0875], "uv_size": [3.0625, 1.625]},
								"south": {"uv": [49.75, 7.5], "uv_size": [3.6875, 0.3125]},
								"west": {"uv": [47.5, 7.125], "uv_size": [3.8125, 1.375]},
								"up": {"uv": [20.125, 86.75], "uv_size": [3.5625, 1.375]},
								"down": {"uv": [49.0625, 8.9375], "uv_size": [4.9375, -1.375]}
							}
						}
					]
				},
				{
					"name": "top_blade2",
					"parent": "nichirintou",
					"pivot": [-5, -5.99908, -58.13811],
					"rotation": [-80, 0, 0]
				},
				{
					"name": "body6",
					"parent": "top_blade2",
					"pivot": [-5, -5.99908, -58.13811]
				},
				{
					"name": "peak25",
					"parent": "body6",
					"pivot": [-5, -5.99908, -58.13811],
					"cubes": [
						{
							"origin": [-6, -6.09908, -87.73811],
							"size": [1, 2, 21.4],
							"uv": {
								"north": {"uv": [14.375, 86.8125], "uv_size": [8, 1.6875]},
								"east": {"uv": [0.5625, 86.5], "uv_size": [48.625, 2.375]},
								"south": {"uv": [67, 10], "uv_size": [12, 3]},
								"west": {"uv": [0.875, 86.75], "uv_size": [34, 2.1875]},
								"up": {"uv": [13, 87.0625], "uv_size": [34.1875, 1.5625]},
								"down": {"uv": [15.8125, 88.5], "uv_size": [31.3125, -1.6875]}
							}
						}
					]
				},
				{
					"name": "body7",
					"parent": "body6",
					"pivot": [-5, -5.99908, -58.13811]
				},
				{
					"name": "blade23",
					"parent": "body7",
					"pivot": [-5, -5.99908, -58.13811],
					"rotation": [0, 0, -12.5],
					"cubes": [
						{
							"origin": [-6, -7.77531, -86.13811],
							"size": [0, 1.9, 19.8],
							"uv": {
								"north": {"uv": [0, 0], "uv_size": [0, 1.9375]},
								"east": {"uv": [10.4375, 79.3125], "uv_size": [37.1875, 2.375]},
								"south": {"uv": [0, 0], "uv_size": [0, 1.9375]},
								"west": {"uv": [0, 20], "uv_size": [81.8125, 1.9375]},
								"up": {"uv": [80, 22], "uv_size": [-80, -1.1875]},
								"down": {"uv": [81, 21.8125], "uv_size": [-68, -0.8125]}
							}
						}
					]
				},
				{
					"name": "blade47",
					"parent": "body7",
					"pivot": [-5, -7.89908, -82.33811],
					"rotation": [0, 0, 16.5],
					"cubes": [
						{
							"origin": [-5.51123, -8.1, -86.13811],
							"size": [0, 1.9, 19.8],
							"uv": {
								"north": {"uv": [0, 0], "uv_size": [0, 2]},
								"east": {"uv": [0, 20], "uv_size": [81.8125, 2]},
								"south": {"uv": [0, 0], "uv_size": [0, 2]},
								"west": {"uv": [9.125, 79], "uv_size": [36.5625, 2.9375]},
								"up": {"uv": [82, 21], "uv_size": [-82, 0.8125]},
								"down": {"uv": [81, 21.8125], "uv_size": [-81, -0.8125]}
							}
						}
					]
				},
				{
					"name": "top3",
					"parent": "top_blade2",
					"pivot": [-5, -5.99908, -74.13811]
				},
				{
					"name": "left3",
					"parent": "top3",
					"pivot": [-2.1, -6.49908, -86.63811],
					"rotation": [-0.08748, -4.99924, 1.2]
				},
				{
					"name": "blade48",
					"parent": "left3",
					"pivot": [-4.80481, -6.89579, -87.85349],
					"rotation": [-3.3024, 4.95122, 14.53016],
					"cubes": [
						{
							"origin": [-5.32284, -8.07593, -86.81823],
							"size": [0, 2, 1],
							"uv": {
								"north": {"uv": [37, 16], "uv_size": [14, 4]},
								"east": {"uv": [51, 17], "uv_size": [11, 3]},
								"south": {"uv": [36, 16], "uv_size": [14, 4]},
								"west": {"uv": [32.1875, 78.225], "uv_size": [2.8625, 3.525]},
								"up": {"uv": [50, 16], "uv_size": [-13, 4]},
								"down": {"uv": [50, 20], "uv_size": [-12, -4]}
							}
						}
					]
				},
				{
					"name": "blade49",
					"parent": "left3",
					"pivot": [-5.65481, -7.79579, -88.50349],
					"rotation": [-4.05259, 7.53866, 13.91607],
					"cubes": [
						{
							"origin": [-5.7231, -7.86301, -87.81815],
							"size": [0, 2, 1],
							"uv": {
								"north": {"uv": [42, 16], "uv_size": [9, 4]},
								"east": {"uv": [49, 16], "uv_size": [10, 3]},
								"south": {"uv": [45, 16], "uv_size": [11, 4]},
								"west": {"uv": [23, 78.875], "uv_size": [-3.1875, 3]},
								"up": {"uv": [56, 17], "uv_size": [-13, 4]},
								"down": {"uv": [56, 20], "uv_size": [-9, -4]}
							}
						}
					]
				},
				{
					"name": "blade50",
					"parent": "left3",
					"pivot": [-5.65481, -8.09579, -88.00349],
					"rotation": [-6.82411, 7.79074, 13.46097],
					"cubes": [
						{
							"origin": [-5.7247, -7.91358, -88.85476],
							"size": [0, 2, 1],
							"uv": {
								"north": {"uv": [40, 16], "uv_size": [13, 4]},
								"east": {"uv": [47, 17], "uv_size": [9, 3]},
								"south": {"uv": [43, 16], "uv_size": [14, 4]},
								"west": {"uv": [8.375, 78.8125], "uv_size": [3.875, 2.875]},
								"up": {"uv": [55, 16], "uv_size": [-11, 4]},
								"down": {"uv": [53, 20], "uv_size": [-10, -4]}
							}
						}
					]
				},
				{
					"name": "blade51",
					"parent": "left3",
					"pivot": [-5.75481, -7.69579, -89.10349],
					"rotation": [-18.87787, 10.68414, 12.67494],
					"cubes": [
						{
							"origin": [-5.80104, -7.68125, -89.80203],
							"size": [0, 1.9, 1],
							"uv": {
								"north": {"uv": [35, 16], "uv_size": [8, 3.875]},
								"east": {"uv": [35, 16], "uv_size": [12, 3.875]},
								"south": {"uv": [35, 15], "uv_size": [9, 3.875]},
								"west": {"uv": [37.4375, 77.9375], "uv_size": [-5, 3.875]},
								"up": {"uv": [44, 16], "uv_size": [-10, 3]},
								"down": {"uv": [46, 20], "uv_size": [-9, -4]}
							}
						}
					]
				},
				{
					"name": "blade52",
					"parent": "left3",
					"pivot": [-5.85481, -7.29579, -90.00349],
					"rotation": [-21.67613, 11.51727, 11.62999],
					"cubes": [
						{
							"origin": [-5.89189, -7.31893, -90.71284],
							"size": [0, 1.7, 1],
							"uv": {
								"north": {"uv": [19, 16], "uv_size": [8, 3.6875]},
								"east": {"uv": [25, 16], "uv_size": [14, 3.6875]},
								"south": {"uv": [5, 16], "uv_size": [11, 3.6875]},
								"west": {"uv": [31.6625, 79.3625], "uv_size": [5.0125, 2.75]},
								"up": {"uv": [17, 15], "uv_size": [-11, 4]},
								"down": {"uv": [18, 20], "uv_size": [-10, -4]}
							}
						}
					]
				},
				{
					"name": "blade53",
					"parent": "left3",
					"pivot": [-5.55481, -6.99579, -90.90349],
					"rotation": [-32.05894, 13.63032, 9.88934],
					"cubes": [
						{
							"origin": [-6.0093, -7.00208, -91.72228],
							"size": [0, 1.3, 1],
							"uv": {
								"north": {"uv": [9, 16], "uv_size": [12, 3.3125]},
								"east": {"uv": [54, 16], "uv_size": [12, 4.3125]},
								"south": {"uv": [21, 16], "uv_size": [10, 4.3125]},
								"west": {"uv": [19.75, 78.1], "uv_size": [3.625, 3.525]},
								"up": {"uv": [37, 16], "uv_size": [-12, 4]},
								"down": {"uv": [37, 21], "uv_size": [-11, -5]}
							}
						}
					]
				},
				{
					"name": "blade54",
					"parent": "left3",
					"pivot": [-6.05481, -6.29579, -91.80349],
					"rotation": [-37.37748, 12.53778, 7.98779],
					"cubes": [
						{
							"origin": [-6.12024, -6.23436, -92.44176],
							"size": [0, 1.2, 1],
							"uv": {
								"north": {"uv": [34, 16], "uv_size": [13, 3.1875]},
								"east": {"uv": [43, 16], "uv_size": [12, 4.1875]},
								"south": {"uv": [36, 16], "uv_size": [13, 4.1875]},
								"west": {"uv": [19.1875, 79.1875], "uv_size": [4.1875, 2.6875]},
								"up": {"uv": [45, 15], "uv_size": [-10, 5]},
								"down": {"uv": [46, 20], "uv_size": [-10, -3]}
							}
						}
					]
				},
				{
					"name": "blade55",
					"parent": "left3",
					"pivot": [-6.15481, -5.79579, -90.50349],
					"rotation": [-65.2931, 13.21654, 4.12416],
					"cubes": [
						{
							"origin": [-5.75867, -7.36527, -91.98775],
							"size": [0, 1.1, 1],
							"uv": {
								"north": {"uv": [3, 15], "uv_size": [13, 3.125]},
								"east": {"uv": [17, 16], "uv_size": [11, 3.125]},
								"south": {"uv": [6, 16], "uv_size": [9, 4.125]},
								"west": {"uv": [44.5, 79.0875], "uv_size": [4.1875, 2.525]},
								"up": {"uv": [16, 15], "uv_size": [-11, 3]},
								"down": {"uv": [18, 19], "uv_size": [-14, -3]}
							}
						}
					]
				},
				{
					"name": "blade56",
					"parent": "left3",
					"pivot": [-6.05481, -4.99579, -92.20349],
					"rotation": [-76.42207, 16.57181, 3.02557],
					"cubes": [
						{
							"origin": [-6.08, -5.40908, -92.57048],
							"size": [0, 1, 1],
							"uv": {
								"north": {"uv": [4, 16], "uv_size": [9, 4]},
								"east": {"uv": [32, 15], "uv_size": [12, 5]},
								"south": {"uv": [22, 15], "uv_size": [10, 5]},
								"west": {"uv": [32.375, 78.975], "uv_size": [3.375, 2.7125]},
								"up": {"uv": [22, 16], "uv_size": [-13, 4]},
								"down": {"uv": [15, 20], "uv_size": [-12, -4]}
							}
						}
					]
				},
				{
					"name": "blade57",
					"parent": "left3",
					"pivot": [-6.05481, -4.89579, -92.30349],
					"rotation": [-91.46404, 15.65073, -1.33709],
					"cubes": [
						{
							"origin": [-6.10031, -5.27668, -93.01811],
							"size": [0, 1.1, 0.8],
							"uv": {
								"north": {"uv": [24, 16], "uv_size": [6, 4.125]},
								"east": {"uv": [41, 17], "uv_size": [8.8125, 4.125]},
								"south": {"uv": [12, 17], "uv_size": [13, 3.125]},
								"west": {"uv": [32, 79.1625], "uv_size": [3.25, 2.6375]},
								"up": {"uv": [29, 16], "uv_size": [-8, 3.8125]},
								"down": {"uv": [39.1875, 89.125], "uv_size": [-7.5, -2.125]}
							}
						}
					]
				},
				{
					"name": "right3",
					"parent": "top3",
					"pivot": [-8.1, -6.99908, -86.63811],
					"rotation": [1.38143, -4.80584, -15.86179]
				},
				{
					"name": "blade58",
					"parent": "right3",
					"pivot": [-6.00481, -6.89579, -86.85349],
					"rotation": [-4.26882, 3.36647, 2.54607],
					"cubes": [
						{
							"origin": [-5.8473, -8.61058, -87.22056],
							"size": [0, 2, 1],
							"uv": {
								"north": {"uv": [51, 16], "uv_size": [11, 3]},
								"east": {"uv": [19.4375, 79.0625], "uv_size": [3.625, 2.75]},
								"south": {"uv": [49, 16], "uv_size": [9, 3]},
								"west": {"uv": [55, 16], "uv_size": [8, 3]},
								"up": {"uv": [0, 0], "uv_size": [0, 1]},
								"down": {"uv": [62, 19], "uv_size": [-12, -3]}
							}
						}
					]
				},
				{
					"name": "blade59",
					"parent": "right3",
					"pivot": [-6.15481, -7.09579, -87.70349],
					"rotation": [-7.50842, 4.54941, 2.13013],
					"cubes": [
						{
							"origin": [-5.92931, -8.51485, -88.14612],
							"size": [0, 1.9, 1],
							"uv": {
								"north": {"uv": [49, 17], "uv_size": [12, 2.875]},
								"east": {"uv": [46.375, 78.625], "uv_size": [2.6875, 3.0625]},
								"south": {"uv": [51, 17], "uv_size": [13, 2.875]},
								"west": {"uv": [64, 16], "uv_size": [9, 1.875]},
								"up": {"uv": [63, 17], "uv_size": [-12, 2]},
								"down": {"uv": [62, 19], "uv_size": [-10, -2]}
							}
						}
					]
				},
				{
					"name": "blade60",
					"parent": "right3",
					"pivot": [-5.95481, -7.09579, -88.50349],
					"rotation": [-10.50842, 4.54941, 2.13013],
					"cubes": [
						{
							"origin": [-5.99199, -8.42008, -89.07023],
							"size": [0, 1.9, 1],
							"uv": {
								"north": {"uv": [53, 17], "uv_size": [10, 2.875]},
								"east": {"uv": [8.5625, 79.1875], "uv_size": [2.8625, 2.5625]},
								"south": {"uv": [54, 17], "uv_size": [10, 2.875]},
								"west": {"uv": [57, 17], "uv_size": [9, 2.875]},
								"up": {"uv": [63, 17], "uv_size": [-8, 3]},
								"down": {"uv": [65, 20], "uv_size": [-8, -3]}
							}
						}
					]
				},
				{
					"name": "blade61",
					"parent": "right3",
					"pivot": [-5.95481, -7.09579, -89.50349],
					"rotation": [-19.4536, 1.72108, 3.13201],
					"cubes": [
						{
							"origin": [-6.04043, -8.15954, -89.91112],
							"size": [0, 1.8, 1],
							"uv": {
								"north": {"uv": [30, 15], "uv_size": [5, 1.8125]},
								"east": {"uv": [19.9375, 81.25], "uv_size": [3.25, -3.0625]},
								"south": {"uv": [29, 17], "uv_size": [7, 1.8125]},
								"west": {"uv": [32, 16], "uv_size": [7, 2.8125]},
								"up": {"uv": [38, 16], "uv_size": [-8, 2]},
								"down": {"uv": [37, 19], "uv_size": [-5, -2]}
							}
						}
					]
				},
				{
					"name": "blade62",
					"parent": "right3",
					"pivot": [-6.15481, -7.49579, -91.10349],
					"rotation": [-33.46247, -1.27178, 3.73827],
					"cubes": [
						{
							"origin": [-6.07578, -7.54045, -92.16797],
							"size": [0, 1.4, 1.1],
							"uv": {
								"north": {"uv": [19, 16], "uv_size": [9, 3.375]},
								"east": {"uv": [32.5625, 81.75], "uv_size": [4.0625, -2.8125]},
								"south": {"uv": [19, 16], "uv_size": [10, 3.375]},
								"west": {"uv": [20, 17], "uv_size": [10.125, 2.375]},
								"up": {"uv": [28, 16], "uv_size": [-9, 3.125]},
								"down": {"uv": [29, 16.125], "uv_size": [-8, 2.875]}
							}
						}
					]
				},
				{
					"name": "blade63",
					"parent": "right3",
					"pivot": [-6.15481, -7.89579, -90.30349],
					"rotation": [-24.45405, 0.39685, 2.63562],
					"cubes": [
						{
							"origin": [-6.08863, -7.90793, -91.26171],
							"size": [0, 1.6, 1.1],
							"uv": {
								"north": {"uv": [5, 16], "uv_size": [9, 1.625]},
								"east": {"uv": [45.125, 82.075], "uv_size": [3.5875, -3.2625]},
								"south": {"uv": [4, 16], "uv_size": [7, 2.625]},
								"west": {"uv": [7, 16], "uv_size": [8.125, 2.625]},
								"up": {"uv": [11, 16], "uv_size": [-7, 2.125]},
								"down": {"uv": [12, 18.125], "uv_size": [-8, -2.125]}
							}
						}
					]
				},
				{
					"name": "blade64",
					"parent": "right3",
					"pivot": [-5.95481, -5.39579, -92.10349],
					"rotation": [-39.3552, -4.72115, 2.68873],
					"cubes": [
						{
							"origin": [-5.90378, -6.50467, -92.04833],
							"size": [0, 1.1, 1.1],
							"uv": {
								"north": {"uv": [7, 16], "uv_size": [11, 3.125]},
								"east": {"uv": [32.875, 81.9375], "uv_size": [3.5, -3.5625]},
								"south": {"uv": [6, 17], "uv_size": [10, 3.125]},
								"west": {"uv": [10, 16], "uv_size": [10.125, 2.125]},
								"up": {"uv": [18, 16], "uv_size": [-11, 3.125]},
								"down": {"uv": [19, 19.125], "uv_size": [-13, -3.125]}
							}
						}
					]
				},
				{
					"name": "blade65",
					"parent": "right3",
					"pivot": [-5.95481, -5.79579, -91.80349],
					"rotation": [-66.59739, -10.04566, 8.44216],
					"cubes": [
						{
							"origin": [-5.99209, -6.909, -92.70198],
							"size": [0, 1, 1],
							"uv": {
								"north": {"uv": [3, 16], "uv_size": [10, 3]},
								"east": {"uv": [45.25, 81.4875], "uv_size": [4, -2.675]},
								"south": {"uv": [6, 16], "uv_size": [10, 4]},
								"west": {"uv": [10, 16], "uv_size": [9, 2]},
								"up": {"uv": [17, 16], "uv_size": [-11, 3]},
								"down": {"uv": [16, 20], "uv_size": [-10, -4]}
							}
						}
					]
				},
				{
					"name": "blade66",
					"parent": "right3",
					"pivot": [-5.95481, -6.49579, -92.10349],
					"rotation": [-78.56771, -10.98354, 12.11256],
					"cubes": [
						{
							"origin": [-6.11486, -7.28665, -93.97791],
							"size": [0, 1, 0.8],
							"uv": {
								"north": {"uv": [8, 16], "uv_size": [9, 4]},
								"east": {"uv": [30.25, 86.8875], "uv_size": [6.65, 1.6125]},
								"south": {"uv": [8, 17], "uv_size": [9, 3]},
								"west": {"uv": [22, 16], "uv_size": [13.8125, 4]},
								"up": {"uv": [16, 16], "uv_size": [-10, 3.8125]},
								"down": {"uv": [15, 18.8125], "uv_size": [-7, -3.8125]}
							}
						}
					]
				},
				{
					"name": "blade67",
					"parent": "right3",
					"pivot": [-5.75481, -5.39579, -92.80349],
					"rotation": [-91.70789, -8.42554, 16.83428],
					"cubes": [
						{
							"origin": [-5.77, -5.77668, -93.51811],
							"size": [0, 1, 0.9],
							"uv": {
								"north": {"uv": [0, 0], "uv_size": [0, 1]},
								"east": {"uv": [32.5, 82.0375], "uv_size": [4.275, -2.975]},
								"south": {"uv": [0, 0], "uv_size": [0, 1]},
								"west": {"uv": [67, 16], "uv_size": [5.875, 3]},
								"up": {"uv": [0, 0], "uv_size": [0, 0.875]},
								"down": {"uv": [0, 0.875], "uv_size": [0, -0.875]}
							}
						}
					]
				},
				{
					"name": "peak26",
					"parent": "top3",
					"pivot": [-5, -5.99908, -74.13811]
				},
				{
					"name": "peak27",
					"parent": "peak26",
					"pivot": [-5, -5.99908, -86.13811],
					"rotation": [0, 1, 0],
					"cubes": [
						{
							"origin": [-5, -6.09908, -87.93811],
							"size": [0, 2, 1.7],
							"uv": {
								"north": {"uv": [0, 0], "uv_size": [0, 2]},
								"east": {"uv": [46, 8], "uv_size": [1.6875, 2]},
								"south": {"uv": [0, 0], "uv_size": [0, 2]},
								"west": {"uv": [14.9375, 86.9375], "uv_size": [1.6875, 2]},
								"up": {"uv": [0, 0], "uv_size": [0, 1.6875]},
								"down": {"uv": [0, 1.6875], "uv_size": [0, -1.6875]}
							}
						}
					]
				},
				{
					"name": "peak28",
					"parent": "peak26",
					"pivot": [-5, -5.49908, -87.93811],
					"rotation": [0, 4, 0],
					"cubes": [
						{
							"origin": [-5.64418, -6.00224, -89.1407],
							"size": [0.6, 1.9, 1.5],
							"uv": {
								"north": {"uv": [34.25, 86.375], "uv_size": [4.75, 2.375]},
								"east": {"uv": [54.4375, 7.25], "uv_size": [3.8125, 1.375]},
								"south": {"uv": [55.25, 7.375], "uv_size": [3.125, 1.375]},
								"west": {"uv": [19.875, 87], "uv_size": [2.375, 1.5]},
								"up": {"uv": [19.5625, 86.375], "uv_size": [3.625, 1.25]},
								"down": {"uv": [16.1875, 88.4375], "uv_size": [7.125, -1.375]}
							}
						}
					]
				},
				{
					"name": "peak29",
					"parent": "peak26",
					"pivot": [-5.2, -4.09908, -89.13811],
					"rotation": [0.07011, 5.99909, 1.00459],
					"cubes": [
						{
							"origin": [-5.62856, -5.89347, -90.22842],
							"size": [0.5, 1.8, 1.2],
							"uv": {
								"north": {"uv": [26.75, 86.5625], "uv_size": [3.4375, 1.875]},
								"east": {"uv": [56, 7.375], "uv_size": [4.75, 1]},
								"south": {"uv": [58.1875, 7.3125], "uv_size": [3, 1.625]},
								"west": {"uv": [24, 87.1875], "uv_size": [2.1875, 1.375]},
								"up": {"uv": [19.4375, 87], "uv_size": [4.1875, 1.5625]},
								"down": {"uv": [32.375, 88.4375], "uv_size": [6.875, -1.5625]}
							}
						}
					]
				},
				{
					"name": "peak30",
					"parent": "peak26",
					"pivot": [-5.1, -4.09908, -90.23811],
					"rotation": [0.14025, 5.99755, 2.00979],
					"cubes": [
						{
							"origin": [-5.54312, -5.69775, -91.2449],
							"size": [0.3, 1.6, 1.1],
							"uv": {
								"north": {"uv": [27.75, 86.875], "uv_size": [3.25, 1.375]},
								"east": {"uv": [71, 10], "uv_size": [7.125, 2.625]},
								"south": {"uv": [62, 9], "uv_size": [10.3125, 3.625]},
								"west": {"uv": [32.375, 86.6875], "uv_size": [2.625, 2]},
								"up": {"uv": [22.6875, 87.125], "uv_size": [3.9375, 1.25]},
								"down": {"uv": [60, 13.125], "uv_size": [7.3125, -3.125]}
							}
						}
					]
				},
				{
					"name": "peak31",
					"parent": "peak26",
					"pivot": [-5.1, -4.09908, -91.23811],
					"rotation": [0.14025, 5.99755, 2.00979],
					"cubes": [
						{
							"origin": [-5.64312, -5.19775, -91.9449],
							"size": [0.3, 1.1, 0.8],
							"uv": {
								"north": {"uv": [32.4375, 86.75], "uv_size": [5.25, 1.25]},
								"east": {"uv": [64.3125, 7.3125], "uv_size": [1.5625, 1.375]},
								"south": {"uv": [65.6875, 7.25], "uv_size": [3.875, 1.25]},
								"west": {"uv": [17.6625, 86.8375], "uv_size": [3.6875, 1.375]},
								"up": {"uv": [17.1875, 87.4375], "uv_size": [4.25, 1.1875]},
								"down": {"uv": [37.6875, 88.1875], "uv_size": [4.125, -1.3125]}
							}
						}
					]
				},
				{
					"name": "peak32",
					"parent": "peak26",
					"pivot": [-5, -5.99908, -86.13811],
					"rotation": [0, 1, 0],
					"cubes": [
						{
							"origin": [-6, -6.09908, -87.83811],
							"size": [0, 2, 1.7],
							"uv": {
								"north": {"uv": [27, 9], "uv_size": [13, 4]},
								"east": {"uv": [7.5625, 86.6875], "uv_size": [3.375, 2.1875]},
								"south": {"uv": [28, 9], "uv_size": [12, 4]},
								"west": {"uv": [39, 8], "uv_size": [7.6875, 4]},
								"up": {"uv": [39, 9], "uv_size": [-12, 3.6875]},
								"down": {"uv": [40, 12.6875], "uv_size": [-13, -3.6875]}
							}
						}
					]
				},
				{
					"name": "peak33",
					"parent": "peak26",
					"pivot": [-6, -5.49908, -87.93811],
					"rotation": [0.01745, -0.99985, -1.00015],
					"cubes": [
						{
							"origin": [-6, -6.00224, -89.2407],
							"size": [0.5, 1.9, 1.5],
							"uv": {
								"north": {"uv": [46, 7.25], "uv_size": [5.3125, 1]},
								"east": {"uv": [16.25, 87.125], "uv_size": [4.25, 1.5625]},
								"south": {"uv": [45.3125, 7.875], "uv_size": [2.8125, 1.5625]},
								"west": {"uv": [42.875, 7.375], "uv_size": [3.75, 1.4375]},
								"up": {"uv": [34.4375, 86.875], "uv_size": [3.4375, 2.125]},
								"down": {"uv": [43.75, 8.6875], "uv_size": [4.625, -1.375]}
							}
						}
					]
				},
				{
					"name": "peak34",
					"parent": "peak26",
					"pivot": [-6, -4.29908, -88.93811],
					"rotation": [0.06983, -3.00091, 0.99361],
					"cubes": [
						{
							"origin": [-6.01565, -5.77934, -90.14383],
							"size": [0.4, 1.7, 1.2],
							"uv": {
								"north": {"uv": [42.625, 7.1875], "uv_size": [2.375, 2.375]},
								"east": {"uv": [19.3125, 87.3125], "uv_size": [3.0625, 1.5]},
								"south": {"uv": [41.375, 7.625], "uv_size": [1.6875, 1.125]},
								"west": {"uv": [39.125, 7.125], "uv_size": [4.25, 1.0625]},
								"up": {"uv": [33.875, 86.5625], "uv_size": [5.0625, 2.125]},
								"down": {"uv": [54.4375, 8.8125], "uv_size": [1.6875, -1.5]}
							}
						}
					]
				},
				{
					"name": "peak35",
					"parent": "peak26",
					"pivot": [-5.8, -4.09908, -90.23811],
					"rotation": [0.24428, -1.99573, -0.01064],
					"cubes": [
						{
							"origin": [-5.94312, -5.74775, -91.0449],
							"size": [0.6, 1.65, 1],
							"uv": {
								"north": {"uv": [16.5, 86.625], "uv_size": [6.1875, 1.875]},
								"east": {"uv": [20.4625, 86.7], "uv_size": [2.975, 1.95]},
								"south": {"uv": [43.4375, 7.375], "uv_size": [4.6875, 1.1875]},
								"west": {"uv": [37.8, 87.2125], "uv_size": [2.875, 1.2875]},
								"up": {"uv": [21.75, 86.75], "uv_size": [4.3125, 1.5625]},
								"down": {"uv": [26.25, 88.625], "uv_size": [3.9375, -1.8125]}
							}
						}
					]
				},
				{
					"name": "peak36",
					"parent": "peak26",
					"pivot": [-5.8, -5.49908, -91.23811],
					"rotation": [0.47007, -1.99324, 0.00414],
					"cubes": [
						{
							"origin": [-5.91799, -5.44802, -91.93386],
							"size": [0.3, 1.35, 0.9],
							"uv": {
								"north": {"uv": [71.3125, 7.375], "uv_size": [3.5625, 1.75]},
								"east": {"uv": [18.875, 87.0875], "uv_size": [3.0625, 1.625]},
								"south": {"uv": [49.75, 7.5], "uv_size": [3.6875, 0.3125]},
								"west": {"uv": [47.5, 7.125], "uv_size": [3.8125, 1.375]},
								"up": {"uv": [20.125, 86.75], "uv_size": [3.5625, 1.375]},
								"down": {"uv": [49.0625, 8.9375], "uv_size": [4.9375, -1.375]}
							}
						}
					]
				},
				{
					"name": "top_blade3",
					"parent": "nichirintou",
					"pivot": [-6, 1.75092, -44.13811],
					"rotation": [-82.5, 0, 180]
				},
				{
					"name": "body8",
					"parent": "top_blade3",
					"pivot": [-6, 1.75092, -44.13811]
				},
				{
					"name": "peak37",
					"parent": "body8",
					"pivot": [-6, 1.75092, -44.13811],
					"cubes": [
						{
							"origin": [-7, 1.65092, -64.23811],
							"size": [1, 2, 18.4],
							"uv": {
								"north": {"uv": [14.375, 86.8125], "uv_size": [8, 1.6875]},
								"east": {"uv": [0.5625, 86.5], "uv_size": [48.625, 2.375]},
								"south": {"uv": [34.5, 87.375], "uv_size": [6.0625, 1.1875]},
								"west": {"uv": [0.875, 86.75], "uv_size": [34, 2.1875]},
								"up": {"uv": [13, 87.0625], "uv_size": [34.1875, 1.5625]},
								"down": {"uv": [15.8125, 88.5], "uv_size": [31.3125, -1.6875]}
							}
						}
					]
				},
				{
					"name": "body9",
					"parent": "body8",
					"pivot": [-6, 1.75092, -44.13811]
				},
				{
					"name": "blade68",
					"parent": "body9",
					"pivot": [-6, 1.75092, -44.13811],
					"rotation": [0, 0, -12.5],
					"cubes": [
						{
							"origin": [-7, -0.02531, -63.13811],
							"size": [0, 1.9, 16.05],
							"uv": {
								"north": {"uv": [0, 0], "uv_size": [0, 1.9375]},
								"east": {"uv": [9.625, 79.5], "uv_size": [35.5, 2.4375]},
								"south": {"uv": [0, 0], "uv_size": [0, 1.9375]},
								"west": {"uv": [0, 20], "uv_size": [81.8125, 1.9375]},
								"up": {"uv": [80, 22], "uv_size": [-80, -1.1875]},
								"down": {"uv": [81, 21.8125], "uv_size": [-68, -0.8125]}
							}
						}
					]
				},
				{
					"name": "blade69",
					"parent": "body9",
					"pivot": [-6, -0.14908, -68.33811],
					"rotation": [0, 0, 16.5],
					"cubes": [
						{
							"origin": [-6.51123, -0.35, -63.13811],
							"size": [0, 1.9, 16.05],
							"uv": {
								"north": {"uv": [0, 0], "uv_size": [0, 2]},
								"east": {"uv": [0, 20], "uv_size": [81.8125, 2]},
								"south": {"uv": [0, 0], "uv_size": [0, 2]},
								"west": {"uv": [11.125, 79.5], "uv_size": [35.25, 2.4375]},
								"up": {"uv": [82, 21], "uv_size": [-82, 0.8125]},
								"down": {"uv": [81, 21.8125], "uv_size": [-81, -0.8125]}
							}
						}
					]
				},
				{
					"name": "top4",
					"parent": "top_blade3",
					"pivot": [-6, 1.75092, -50.63811]
				},
				{
					"name": "left4",
					"parent": "top4",
					"pivot": [-3.1, 1.25092, -63.13811],
					"rotation": [-0.08748, -4.99924, 1.2]
				},
				{
					"name": "blade70",
					"parent": "left4",
					"pivot": [-5.80481, 0.85421, -64.35349],
					"rotation": [-3.3024, 4.95122, 14.53016],
					"cubes": [
						{
							"origin": [-6.32284, -0.32593, -63.31823],
							"size": [0, 2, 1],
							"uv": {
								"north": {"uv": [37, 16], "uv_size": [14, 4]},
								"east": {"uv": [51, 17], "uv_size": [11, 3]},
								"south": {"uv": [36, 16], "uv_size": [14, 4]},
								"west": {"uv": [32.1875, 78.225], "uv_size": [2.8625, 3.525]},
								"up": {"uv": [50, 16], "uv_size": [-13, 4]},
								"down": {"uv": [50, 20], "uv_size": [-12, -4]}
							}
						}
					]
				},
				{
					"name": "blade71",
					"parent": "left4",
					"pivot": [-6.65481, -0.04579, -65.00349],
					"rotation": [-4.05259, 7.53866, 13.91607],
					"cubes": [
						{
							"origin": [-6.7231, -0.11301, -64.31815],
							"size": [0, 2, 1],
							"uv": {
								"north": {"uv": [42, 16], "uv_size": [9, 4]},
								"east": {"uv": [49, 16], "uv_size": [10, 3]},
								"south": {"uv": [45, 16], "uv_size": [11, 4]},
								"west": {"uv": [23, 78.875], "uv_size": [-3.1875, 3]},
								"up": {"uv": [56, 17], "uv_size": [-13, 4]},
								"down": {"uv": [56, 20], "uv_size": [-9, -4]}
							}
						}
					]
				},
				{
					"name": "blade72",
					"parent": "left4",
					"pivot": [-6.65481, -0.34579, -64.50349],
					"rotation": [-6.82411, 7.79074, 13.46097],
					"cubes": [
						{
							"origin": [-6.7247, -0.16358, -65.35476],
							"size": [0, 2, 1],
							"uv": {
								"north": {"uv": [40, 16], "uv_size": [13, 4]},
								"east": {"uv": [47, 17], "uv_size": [9, 3]},
								"south": {"uv": [43, 16], "uv_size": [14, 4]},
								"west": {"uv": [8.375, 78.8125], "uv_size": [3.875, 2.875]},
								"up": {"uv": [55, 16], "uv_size": [-11, 4]},
								"down": {"uv": [53, 20], "uv_size": [-10, -4]}
							}
						}
					]
				},
				{
					"name": "blade73",
					"parent": "left4",
					"pivot": [-6.75481, 0.05421, -65.60349],
					"rotation": [-18.87787, 10.68414, 12.67494],
					"cubes": [
						{
							"origin": [-6.80104, 0.06875, -66.30203],
							"size": [0, 1.9, 1],
							"uv": {
								"north": {"uv": [35, 16], "uv_size": [8, 3.875]},
								"east": {"uv": [35, 16], "uv_size": [12, 3.875]},
								"south": {"uv": [35, 15], "uv_size": [9, 3.875]},
								"west": {"uv": [37.4375, 77.9375], "uv_size": [-5, 3.875]},
								"up": {"uv": [44, 16], "uv_size": [-10, 3]},
								"down": {"uv": [46, 20], "uv_size": [-9, -4]}
							}
						}
					]
				},
				{
					"name": "blade74",
					"parent": "left4",
					"pivot": [-6.85481, 0.45421, -66.50349],
					"rotation": [-21.67613, 11.51727, 11.62999],
					"cubes": [
						{
							"origin": [-6.89189, 0.43107, -67.21284],
							"size": [0, 1.7, 1],
							"uv": {
								"north": {"uv": [19, 16], "uv_size": [8, 3.6875]},
								"east": {"uv": [25, 16], "uv_size": [14, 3.6875]},
								"south": {"uv": [5, 16], "uv_size": [11, 3.6875]},
								"west": {"uv": [31.6625, 79.3625], "uv_size": [5.0125, 2.75]},
								"up": {"uv": [17, 15], "uv_size": [-11, 4]},
								"down": {"uv": [18, 20], "uv_size": [-10, -4]}
							}
						}
					]
				},
				{
					"name": "blade75",
					"parent": "left4",
					"pivot": [-6.55481, 0.75421, -67.40349],
					"rotation": [-32.05894, 13.63032, 9.88934],
					"cubes": [
						{
							"origin": [-7.0093, 0.74792, -68.22228],
							"size": [0, 1.3, 1],
							"uv": {
								"north": {"uv": [9, 16], "uv_size": [12, 3.3125]},
								"east": {"uv": [54, 16], "uv_size": [12, 4.3125]},
								"south": {"uv": [21, 16], "uv_size": [10, 4.3125]},
								"west": {"uv": [19.75, 78.1], "uv_size": [3.625, 3.525]},
								"up": {"uv": [37, 16], "uv_size": [-12, 4]},
								"down": {"uv": [37, 21], "uv_size": [-11, -5]}
							}
						}
					]
				},
				{
					"name": "blade76",
					"parent": "left4",
					"pivot": [-7.05481, 1.45421, -68.30349],
					"rotation": [-37.37748, 12.53778, 7.98779],
					"cubes": [
						{
							"origin": [-7.12024, 1.51564, -68.94176],
							"size": [0, 1.2, 1],
							"uv": {
								"north": {"uv": [34, 16], "uv_size": [13, 3.1875]},
								"east": {"uv": [43, 16], "uv_size": [12, 4.1875]},
								"south": {"uv": [36, 16], "uv_size": [13, 4.1875]},
								"west": {"uv": [19.1875, 79.1875], "uv_size": [4.1875, 2.6875]},
								"up": {"uv": [45, 15], "uv_size": [-10, 5]},
								"down": {"uv": [46, 20], "uv_size": [-10, -3]}
							}
						}
					]
				},
				{
					"name": "blade77",
					"parent": "left4",
					"pivot": [-7.15481, 1.95421, -67.00349],
					"rotation": [-65.2931, 13.21654, 4.12416],
					"cubes": [
						{
							"origin": [-6.75867, 0.38473, -68.48775],
							"size": [0, 1.1, 1],
							"uv": {
								"north": {"uv": [3, 15], "uv_size": [13, 3.125]},
								"east": {"uv": [17, 16], "uv_size": [11, 3.125]},
								"south": {"uv": [6, 16], "uv_size": [9, 4.125]},
								"west": {"uv": [44.5, 79.0875], "uv_size": [4.1875, 2.525]},
								"up": {"uv": [16, 15], "uv_size": [-11, 3]},
								"down": {"uv": [18, 19], "uv_size": [-14, -3]}
							}
						}
					]
				},
				{
					"name": "blade78",
					"parent": "left4",
					"pivot": [-7.05481, 2.75421, -68.70349],
					"rotation": [-76.42207, 16.57181, 3.02557],
					"cubes": [
						{
							"origin": [-7.08, 2.34092, -69.07048],
							"size": [0, 1, 1],
							"uv": {
								"north": {"uv": [4, 16], "uv_size": [9, 4]},
								"east": {"uv": [32, 15], "uv_size": [12, 5]},
								"south": {"uv": [22, 15], "uv_size": [10, 5]},
								"west": {"uv": [32.375, 78.975], "uv_size": [3.375, 2.7125]},
								"up": {"uv": [22, 16], "uv_size": [-13, 4]},
								"down": {"uv": [15, 20], "uv_size": [-12, -4]}
							}
						}
					]
				},
				{
					"name": "blade79",
					"parent": "left4",
					"pivot": [-7.05481, 2.85421, -68.80349],
					"rotation": [-91.46404, 15.65073, -1.33709],
					"cubes": [
						{
							"origin": [-7.10031, 2.47332, -69.51811],
							"size": [0, 1.1, 0.8],
							"uv": {
								"north": {"uv": [24, 16], "uv_size": [6, 4.125]},
								"east": {"uv": [41, 17], "uv_size": [8.8125, 4.125]},
								"south": {"uv": [12, 17], "uv_size": [13, 3.125]},
								"west": {"uv": [32, 79.1625], "uv_size": [3.25, 2.6375]},
								"up": {"uv": [29, 16], "uv_size": [-8, 3.8125]},
								"down": {"uv": [39.1875, 89.125], "uv_size": [-7.5, -2.125]}
							}
						}
					]
				},
				{
					"name": "right4",
					"parent": "top4",
					"pivot": [-9.1, 0.75092, -63.13811],
					"rotation": [1.38143, -4.80584, -15.86179]
				},
				{
					"name": "blade80",
					"parent": "right4",
					"pivot": [-7.00481, 0.85421, -63.35349],
					"rotation": [-4.26882, 3.36647, 2.54607],
					"cubes": [
						{
							"origin": [-6.8473, -0.86058, -63.72056],
							"size": [0, 2, 1],
							"uv": {
								"north": {"uv": [51, 16], "uv_size": [11, 3]},
								"east": {"uv": [19.4375, 79.0625], "uv_size": [3.625, 2.75]},
								"south": {"uv": [49, 16], "uv_size": [9, 3]},
								"west": {"uv": [55, 16], "uv_size": [8, 3]},
								"up": {"uv": [0, 0], "uv_size": [0, 1]},
								"down": {"uv": [62, 19], "uv_size": [-12, -3]}
							}
						}
					]
				},
				{
					"name": "blade81",
					"parent": "right4",
					"pivot": [-7.15481, 0.65421, -64.20349],
					"rotation": [-7.50842, 4.54941, 2.13013],
					"cubes": [
						{
							"origin": [-6.92931, -0.76485, -64.64612],
							"size": [0, 1.9, 1],
							"uv": {
								"north": {"uv": [49, 17], "uv_size": [12, 2.875]},
								"east": {"uv": [46.375, 78.625], "uv_size": [2.6875, 3.0625]},
								"south": {"uv": [51, 17], "uv_size": [13, 2.875]},
								"west": {"uv": [64, 16], "uv_size": [9, 1.875]},
								"up": {"uv": [63, 17], "uv_size": [-12, 2]},
								"down": {"uv": [62, 19], "uv_size": [-10, -2]}
							}
						}
					]
				},
				{
					"name": "blade82",
					"parent": "right4",
					"pivot": [-6.95481, 0.65421, -65.00349],
					"rotation": [-10.50842, 4.54941, 2.13013],
					"cubes": [
						{
							"origin": [-6.99199, -0.67008, -65.57023],
							"size": [0, 1.9, 1],
							"uv": {
								"north": {"uv": [53, 17], "uv_size": [10, 2.875]},
								"east": {"uv": [8.5625, 79.1875], "uv_size": [2.8625, 2.5625]},
								"south": {"uv": [54, 17], "uv_size": [10, 2.875]},
								"west": {"uv": [57, 17], "uv_size": [9, 2.875]},
								"up": {"uv": [63, 17], "uv_size": [-8, 3]},
								"down": {"uv": [65, 20], "uv_size": [-8, -3]}
							}
						}
					]
				},
				{
					"name": "blade83",
					"parent": "right4",
					"pivot": [-6.95481, 0.65421, -66.00349],
					"rotation": [-19.4536, 1.72108, 3.13201],
					"cubes": [
						{
							"origin": [-7.04043, -0.40954, -66.41112],
							"size": [0, 1.8, 1],
							"uv": {
								"north": {"uv": [30, 15], "uv_size": [5, 1.8125]},
								"east": {"uv": [19.9375, 81.25], "uv_size": [3.25, -3.0625]},
								"south": {"uv": [29, 17], "uv_size": [7, 1.8125]},
								"west": {"uv": [32, 16], "uv_size": [7, 2.8125]},
								"up": {"uv": [38, 16], "uv_size": [-8, 2]},
								"down": {"uv": [37, 19], "uv_size": [-5, -2]}
							}
						}
					]
				},
				{
					"name": "blade84",
					"parent": "right4",
					"pivot": [-7.15481, 0.25421, -67.60349],
					"rotation": [-33.46247, -1.27178, 3.73827],
					"cubes": [
						{
							"origin": [-7.07578, 0.20955, -68.66797],
							"size": [0, 1.4, 1.1],
							"uv": {
								"north": {"uv": [19, 16], "uv_size": [9, 3.375]},
								"east": {"uv": [32.5625, 81.75], "uv_size": [4.0625, -2.8125]},
								"south": {"uv": [19, 16], "uv_size": [10, 3.375]},
								"west": {"uv": [20, 17], "uv_size": [10.125, 2.375]},
								"up": {"uv": [28, 16], "uv_size": [-9, 3.125]},
								"down": {"uv": [29, 16.125], "uv_size": [-8, 2.875]}
							}
						}
					]
				},
				{
					"name": "blade85",
					"parent": "right4",
					"pivot": [-7.15481, -0.14579, -66.80349],
					"rotation": [-24.45405, 0.39685, 2.63562],
					"cubes": [
						{
							"origin": [-7.08863, -0.15793, -67.76171],
							"size": [0, 1.6, 1.1],
							"uv": {
								"north": {"uv": [5, 16], "uv_size": [9, 1.625]},
								"east": {"uv": [45.125, 82.075], "uv_size": [3.5875, -3.2625]},
								"south": {"uv": [4, 16], "uv_size": [7, 2.625]},
								"west": {"uv": [7, 16], "uv_size": [8.125, 2.625]},
								"up": {"uv": [11, 16], "uv_size": [-7, 2.125]},
								"down": {"uv": [12, 18.125], "uv_size": [-8, -2.125]}
							}
						}
					]
				},
				{
					"name": "blade86",
					"parent": "right4",
					"pivot": [-6.95481, 2.35421, -68.60349],
					"rotation": [-39.3552, -4.72115, 2.68873],
					"cubes": [
						{
							"origin": [-6.90378, 1.24533, -68.54833],
							"size": [0, 1.1, 1.1],
							"uv": {
								"north": {"uv": [7, 16], "uv_size": [11, 3.125]},
								"east": {"uv": [32.875, 81.9375], "uv_size": [3.5, -3.5625]},
								"south": {"uv": [6, 17], "uv_size": [10, 3.125]},
								"west": {"uv": [10, 16], "uv_size": [10.125, 2.125]},
								"up": {"uv": [18, 16], "uv_size": [-11, 3.125]},
								"down": {"uv": [19, 19.125], "uv_size": [-13, -3.125]}
							}
						}
					]
				},
				{
					"name": "blade87",
					"parent": "right4",
					"pivot": [-6.95481, 1.95421, -68.30349],
					"rotation": [-66.59739, -10.04566, 8.44216],
					"cubes": [
						{
							"origin": [-6.99209, 0.841, -69.20198],
							"size": [0, 1, 1],
							"uv": {
								"north": {"uv": [3, 16], "uv_size": [10, 3]},
								"east": {"uv": [45.25, 81.4875], "uv_size": [4, -2.675]},
								"south": {"uv": [6, 16], "uv_size": [10, 4]},
								"west": {"uv": [10, 16], "uv_size": [9, 2]},
								"up": {"uv": [17, 16], "uv_size": [-11, 3]},
								"down": {"uv": [16, 20], "uv_size": [-10, -4]}
							}
						}
					]
				},
				{
					"name": "blade88",
					"parent": "right4",
					"pivot": [-6.95481, 1.25421, -68.60349],
					"rotation": [-78.56771, -10.98354, 12.11256],
					"cubes": [
						{
							"origin": [-7.11486, 0.46335, -70.47791],
							"size": [0, 1, 0.8],
							"uv": {
								"north": {"uv": [8, 16], "uv_size": [9, 4]},
								"east": {"uv": [30.25, 86.8875], "uv_size": [6.65, 1.6125]},
								"south": {"uv": [8, 17], "uv_size": [9, 3]},
								"west": {"uv": [22, 16], "uv_size": [13.8125, 4]},
								"up": {"uv": [16, 16], "uv_size": [-10, 3.8125]},
								"down": {"uv": [15, 18.8125], "uv_size": [-7, -3.8125]}
							}
						}
					]
				},
				{
					"name": "blade89",
					"parent": "right4",
					"pivot": [-6.75481, 2.35421, -69.30349],
					"rotation": [-91.70789, -8.42554, 16.83428],
					"cubes": [
						{
							"origin": [-6.77, 1.97332, -70.01811],
							"size": [0, 1, 0.9],
							"uv": {
								"north": {"uv": [0, 0], "uv_size": [0, 1]},
								"east": {"uv": [32.5, 82.0375], "uv_size": [4.275, -2.975]},
								"south": {"uv": [0, 0], "uv_size": [0, 1]},
								"west": {"uv": [67, 16], "uv_size": [5.875, 3]},
								"up": {"uv": [0, 0], "uv_size": [0, 0.875]},
								"down": {"uv": [0, 0.875], "uv_size": [0, -0.875]}
							}
						}
					]
				},
				{
					"name": "peak38",
					"parent": "top4",
					"pivot": [-6, 1.75092, -50.63811]
				},
				{
					"name": "peak39",
					"parent": "peak38",
					"pivot": [-6, 1.75092, -62.63811],
					"rotation": [0, 1, 0],
					"cubes": [
						{
							"origin": [-6, 1.65092, -64.43811],
							"size": [0, 2, 1.7],
							"uv": {
								"north": {"uv": [0, 0], "uv_size": [0, 2]},
								"east": {"uv": [46, 8], "uv_size": [1.6875, 2]},
								"south": {"uv": [0, 0], "uv_size": [0, 2]},
								"west": {"uv": [14.9375, 86.9375], "uv_size": [1.6875, 2]},
								"up": {"uv": [0, 0], "uv_size": [0, 1.6875]},
								"down": {"uv": [0, 1.6875], "uv_size": [0, -1.6875]}
							}
						}
					]
				},
				{
					"name": "peak40",
					"parent": "peak38",
					"pivot": [-6, 2.25092, -64.43811],
					"rotation": [0, 4, 0],
					"cubes": [
						{
							"origin": [-6.64418, 1.74776, -65.6407],
							"size": [0.6, 1.9, 1.5],
							"uv": {
								"north": {"uv": [34.25, 86.375], "uv_size": [4.75, 2.375]},
								"east": {"uv": [54.4375, 7.25], "uv_size": [3.8125, 1.375]},
								"south": {"uv": [55.25, 7.375], "uv_size": [3.125, 1.375]},
								"west": {"uv": [19.875, 87], "uv_size": [2.375, 1.5]},
								"up": {"uv": [19.5625, 86.375], "uv_size": [3.625, 1.25]},
								"down": {"uv": [16.1875, 88.4375], "uv_size": [7.125, -1.375]}
							}
						}
					]
				},
				{
					"name": "peak41",
					"parent": "peak38",
					"pivot": [-6.2, 3.65092, -65.63811],
					"rotation": [0.07011, 5.99909, 1.00459],
					"cubes": [
						{
							"origin": [-6.62856, 1.85653, -66.72842],
							"size": [0.5, 1.8, 1.2],
							"uv": {
								"north": {"uv": [26.75, 86.5625], "uv_size": [3.4375, 1.875]},
								"east": {"uv": [56, 7.375], "uv_size": [4.75, 1]},
								"south": {"uv": [58.1875, 7.3125], "uv_size": [3, 1.625]},
								"west": {"uv": [24, 87.1875], "uv_size": [2.1875, 1.375]},
								"up": {"uv": [19.4375, 87], "uv_size": [4.1875, 1.5625]},
								"down": {"uv": [32.375, 88.4375], "uv_size": [6.875, -1.5625]}
							}
						}
					]
				},
				{
					"name": "peak42",
					"parent": "peak38",
					"pivot": [-6.1, 3.65092, -66.73811],
					"rotation": [0.14025, 5.99755, 2.00979],
					"cubes": [
						{
							"origin": [-6.54312, 2.05225, -67.7449],
							"size": [0.3, 1.6, 1.1],
							"uv": {
								"north": {"uv": [27.75, 86.875], "uv_size": [3.25, 1.375]},
								"east": {"uv": [71, 10], "uv_size": [7.125, 2.625]},
								"south": {"uv": [62, 9], "uv_size": [10.3125, 3.625]},
								"west": {"uv": [32.375, 86.6875], "uv_size": [2.625, 2]},
								"up": {"uv": [22.6875, 87.125], "uv_size": [3.9375, 1.25]},
								"down": {"uv": [60, 13.125], "uv_size": [7.3125, -3.125]}
							}
						}
					]
				},
				{
					"name": "peak43",
					"parent": "peak38",
					"pivot": [-6.1, 3.65092, -67.73811],
					"rotation": [0.14025, 5.99755, 2.00979],
					"cubes": [
						{
							"origin": [-6.64312, 2.55225, -68.4449],
							"size": [0.3, 1.1, 0.8],
							"uv": {
								"north": {"uv": [32.4375, 86.75], "uv_size": [5.25, 1.25]},
								"east": {"uv": [64.3125, 7.3125], "uv_size": [1.5625, 1.375]},
								"south": {"uv": [65.6875, 7.25], "uv_size": [3.875, 1.25]},
								"west": {"uv": [17.6625, 86.8375], "uv_size": [3.6875, 1.375]},
								"up": {"uv": [17.1875, 87.4375], "uv_size": [4.25, 1.1875]},
								"down": {"uv": [37.6875, 88.1875], "uv_size": [4.125, -1.3125]}
							}
						}
					]
				},
				{
					"name": "peak44",
					"parent": "peak38",
					"pivot": [-6, 1.75092, -62.63811],
					"rotation": [0, 1, 0],
					"cubes": [
						{
							"origin": [-7, 1.65092, -64.33811],
							"size": [0, 2, 1.7],
							"uv": {
								"north": {"uv": [27, 9], "uv_size": [13, 4]},
								"east": {"uv": [7.5625, 86.6875], "uv_size": [3.375, 2.1875]},
								"south": {"uv": [28, 9], "uv_size": [12, 4]},
								"west": {"uv": [39, 8], "uv_size": [7.6875, 4]},
								"up": {"uv": [39, 9], "uv_size": [-12, 3.6875]},
								"down": {"uv": [40, 12.6875], "uv_size": [-13, -3.6875]}
							}
						}
					]
				},
				{
					"name": "peak45",
					"parent": "peak38",
					"pivot": [-7, 2.25092, -64.43811],
					"rotation": [0.01745, -0.99985, -1.00015],
					"cubes": [
						{
							"origin": [-7, 1.74776, -65.7407],
							"size": [0.5, 1.9, 1.5],
							"uv": {
								"north": {"uv": [46, 7.25], "uv_size": [5.3125, 1]},
								"east": {"uv": [16.25, 87.125], "uv_size": [4.25, 1.5625]},
								"south": {"uv": [45.3125, 7.875], "uv_size": [2.8125, 1.5625]},
								"west": {"uv": [42.875, 7.375], "uv_size": [3.75, 1.4375]},
								"up": {"uv": [34.4375, 86.875], "uv_size": [3.4375, 2.125]},
								"down": {"uv": [43.75, 8.6875], "uv_size": [4.625, -1.375]}
							}
						}
					]
				},
				{
					"name": "peak46",
					"parent": "peak38",
					"pivot": [-7, 3.45092, -65.43811],
					"rotation": [0.06983, -3.00091, 0.99361],
					"cubes": [
						{
							"origin": [-7.01565, 1.97066, -66.64383],
							"size": [0.4, 1.7, 1.2],
							"uv": {
								"north": {"uv": [42.625, 7.1875], "uv_size": [2.375, 2.375]},
								"east": {"uv": [19.3125, 87.3125], "uv_size": [3.0625, 1.5]},
								"south": {"uv": [41.375, 7.625], "uv_size": [1.6875, 1.125]},
								"west": {"uv": [39.125, 7.125], "uv_size": [4.25, 1.0625]},
								"up": {"uv": [33.875, 86.5625], "uv_size": [5.0625, 2.125]},
								"down": {"uv": [54.4375, 8.8125], "uv_size": [1.6875, -1.5]}
							}
						}
					]
				},
				{
					"name": "peak47",
					"parent": "peak38",
					"pivot": [-6.8, 3.65092, -66.73811],
					"rotation": [0.24428, -1.99573, -0.01064],
					"cubes": [
						{
							"origin": [-6.94312, 2.00225, -67.5449],
							"size": [0.6, 1.65, 1],
							"uv": {
								"north": {"uv": [16.5, 86.625], "uv_size": [6.1875, 1.875]},
								"east": {"uv": [20.4625, 86.7], "uv_size": [2.975, 1.95]},
								"south": {"uv": [43.4375, 7.375], "uv_size": [4.6875, 1.1875]},
								"west": {"uv": [37.8, 87.2125], "uv_size": [2.875, 1.2875]},
								"up": {"uv": [21.75, 86.75], "uv_size": [4.3125, 1.5625]},
								"down": {"uv": [26.25, 88.625], "uv_size": [3.9375, -1.8125]}
							}
						}
					]
				},
				{
					"name": "peak48",
					"parent": "peak38",
					"pivot": [-6.8, 2.25092, -67.73811],
					"rotation": [0.47007, -1.99324, 0.00414],
					"cubes": [
						{
							"origin": [-6.91799, 2.30198, -68.43386],
							"size": [0.3, 1.35, 0.9],
							"uv": {
								"north": {"uv": [71.3125, 7.375], "uv_size": [3.5625, 1.75]},
								"east": {"uv": [18.875, 87.0875], "uv_size": [3.0625, 1.625]},
								"south": {"uv": [49.75, 7.5], "uv_size": [3.6875, 0.3125]},
								"west": {"uv": [47.5, 7.125], "uv_size": [3.8125, 1.375]},
								"up": {"uv": [20.125, 86.75], "uv_size": [3.5625, 1.375]},
								"down": {"uv": [49.0625, 8.9375], "uv_size": [4.9375, -1.375]}
							}
						}
					]
				}
			]
		}
	]
}