{
	"format_version": "1.8.0",
	"animations": {
		"animation.model.magicenchant.set": {
			"animation_length": 0.5,
			"bones": {
				"top": {
					"position": {
						"0.0": [0, 0, 0],
						"0.5": [0, 3, 0]
					}
				},
				"red": {
					"rotation": {
						"0.0": [0, 0, 0],
						"0.5": [0, 0, 90]
					}
				},
				"bule": {
					"rotation": {
						"0.0": [0, 0, 0],
						"0.5": [90, 0, 0]
					}
				},
				"yellow": {
					"rotation": {
						"0.0": [0, 0, 0],
						"0.5": [-90, 0, 0]
					}
				},
				"gray": {
					"rotation": {
						"0.0": [0, 0, 0],
						"0.5": [-90, 0, 0]
					}
				},
				"green": {
					"rotation": {
						"0.0": [0, 0, 0],
						"0.5": [90, 0, 0]
					}
				}
			}
		},
		"animation.model.magic_table.state": {
			"loop": true,
			"animation_length": 1,
			"bones": {
				"top": {
					"position": [0, 3, 0]
				},
				"red": {
					"rotation": {
						"0.0": [0, 0, 90],
						"0.5": [0, 0, 180],
						"1.0": [0, 0, 270]
					}
				},
				"bule": {
					"rotation": {
						"0.0": [90, 0, 0],
						"0.5": [90, 90, 0],
						"1.0": [90, 180, 0]
					}
				},
				"yellow": {
					"rotation": {
						"0.0": [-90, 0, 0],
						"0.5": [-90, -90, 0],
						"1.0": [-90, -180, 0]
					}
				},
				"gray": {
					"rotation": {
						"0.0": [-90, 0, 0],
						"0.5": [-90, -90, 0],
						"1.0": [-90, -180, 0]
					}
				},
				"green": {
					"rotation": {
						"0.0": [90, 0, 0],
						"0.5": [90, 90, 0],
						"1.0": [90, 180, 0]
					}
				}
			}
		}
	}
}