{
	"format_version": "1.8.0",
	"animations": {
		"animation.barista.empty": {
			"loop": "hold_on_last_frame",
			"bones": {
				"string_right": {
					"rotation": [-3, -30, 6],
					"position": [-1, 6.5, -1],
					"scale": [1.2, 0.2, 0.2]
				},
				"string_left": {
					"rotation": [3, 30, -6],
					"position": [1, 6.5, -0.5],
					"scale": [1.2, 0.2, 0.2]
				},
				"trigger": {
					"position": [0, -0.75, 5.25]
				}
			}
		},
		"animation.barista.charge": {
			"loop": "hold_on_last_frame",
			"animation_length": 0.25,
			"bones": {
				"string_right": {
					"rotation": {
						"0.0": [-3, -30, 6],
						"0.25": [-7.69247, -52.19771, 11.93698]
					},
					"position": {
						"0.0": [-1, 6.5, -1],
						"0.25": [-1, 5.5, 7]
					},
					"scale": [1.2, 0.2, 0.2]
				},
				"string_left": {
					"rotation": {
						"0.0": [3, 30, -6],
						"0.25": [-2.6668, 52.52692, -12.30071]
					},
					"position": {
						"0.0": [1, 6.5, -0.5],
						"0.25": [1, 5.75, 7.5]
					},
					"scale": [1.2, 0.2, 0.2]
				},
				"trigger": {
					"position": {
						"0.0": [0, -0.75, 5.25],
						"0.25": [0, -1.75, 14.25]
					}
				},
				"barrel_left": {
					"rotation": {
						"0.0": [0, 0, 0],
						"0.25": [-1.44261, -29.96852, 2.88614]
					},
					"position": {
						"0.0": [0, 0, 0],
						"0.25": [-7.75, 0, -2.5]
					}
				},
				"barrel_right": {
					"rotation": {
						"0.0": [0, 0, 0],
						"0.25": [-1.44261, 29.96852, -2.88614]
					},
					"position": {
						"0.0": [0, 0, 0],
						"0.25": [7.9, 0, -2.6]
					}
				},
				"arrow": {
					"position": {
						"0.0": [0, 0, 0],
						"0.25": [0, -1, 5]
					}
				}
			}
		}
	}
}