{
  "format_version": "1.12",
  "minecraft:recipe_shapeless": {
    "description": {
      "identifier": "kurokumaft:ice_magic_chestplate_to_magicstone"
    },

    "tags": [ "magic_enchant" ],
    "priority": 3,
    "ingredients": [
      {
        "item": "minecraft:diamond_chestplate"
      },
      {
        "item": "minecraft:blue_ice"
      },
      {
        "item": "kurokumaft:ice_magic_stone"
      }
    ],
    "result": {
      "item": "kurokumaft:ice_magic_chestplate",
      "count": 1
    }
  }
  
}
