{
  "format_version": "1.21.20",
  "minecraft:item": {
    "description": {
      "identifier": "kurokumaft:seeds_pellet_grass",
      "menu_category": {
        "category": "nature"
      }
    },
    "components": {
      "minecraft:display_name": {
				"value": "item.kurokumaft:seeds_pellet_grass.name"
			},
      "minecraft:icon": "seeds_pellet_grass",
      "minecraft:block_placer": {
        "block": "kurokumaft:pellet_grass_bud",
        "use_on" : [
          "farmland","grass","dirt"
        ]
      }
    }
  }
}